Workbook

Sheet Cover
B2: HUBSPOT, INC. (NYSE: HUBS)
B3: Three-Statement Financial Model; SaaS; Customer Platform (CRM, Marketing, Sales & Service)
B4: Integrated Income Statement · Balance Sheet · Cash Flow · driver-based forecast · regional scenarios · live market data
B6: AUTHOR & VERSION
B7: Prepared by: Avash Pardhootman
B8: =HYPERLINK("mailto:avash.pardhootman@gmail.com","Contact: avash.pardhootman@gmail.com") -> Contact: avash.pardhootman@gmail.com
B9: =HYPERLINK("https://www.linkedin.com/in/avashpardhootman/","LinkedIn: linkedin.com/in/avashpardhootman") -> LinkedIn: linkedin.com/in/avashpardhootman
B10: Date: July 2026 · Model version: 1.7 (see Version History) · Units: USD thousands, except per-share
B11: Periods: FY2023–FY2025 actual (per SEC filings) · FY2026–FY2030 forecast
B13: QUICK LINKS
B14: =HYPERLINK("Finance_AI_Dashboard.html","▸ Interactive dashboard · toggle industry, scenario and region in your browser (same folder)") -> ▸ Interactive dashboard · toggle industry, scenario and region in your browser (same folder)
B15: =HYPERLINK("README.md","▸ Portfolio README · overview of all three models and how they fit together") -> ▸ Portfolio README · overview of all three models and how they fit together
B16: =HYPERLINK("refresh_market_data.py","▸ Market-data refresh script · run to update prices, rates and refresh stamps everywhere") -> ▸ Market-data refresh script · run to update prices, rates and refresh stamps everywhere
B18: CONTENTS
B19: =HYPERLINK("#'Assumptions'!A1","▸ Assumptions · Margin, tax, working-capital and financing drivers") -> ▸ Assumptions · Margin, tax, working-capital and financing drivers
B20: =HYPERLINK("#'Revenue Drivers'!A1","▸ Revenue Drivers · Bottoms-up sector build driving revenue and key costs") -> ▸ Revenue Drivers · Bottoms-up sector build driving revenue and key costs
B21: =HYPERLINK("#'Regional Breakdown'!A1","▸ Regional Breakdown · NA / Europe / APAC splits and the Standard / Best / Low case selector") -> ▸ Regional Breakdown · NA / Europe / APAC splits and the Standard / Best / Low case selector
B22: =HYPERLINK("#'Income Statement'!A1","▸ Income Statement · Revenue build-down to EPS") -> ▸ Income Statement · Revenue build-down to EPS
B23: =HYPERLINK("#'Balance Sheet'!A1","▸ Balance Sheet · Assets, liabilities and equity, with balance check") -> ▸ Balance Sheet · Assets, liabilities and equity, with balance check
B24: =HYPERLINK("#'Cash Flow'!A1","▸ Cash Flow · Indirect-method cash flow; ending cash links to the balance sheet") -> ▸ Cash Flow · Indirect-method cash flow; ending cash links to the balance sheet
B25: =HYPERLINK("#'Budget vs Actual'!A1","▸ Budget vs Actual · FY2025 vs guidance with automatic >10% variance flagging") -> ▸ Budget vs Actual · FY2025 vs guidance with automatic >10% variance flagging
B26: =HYPERLINK("#'Market Inputs'!A1","▸ Market Inputs · Rates and valuation multiples with refresh stamps") -> ▸ Market Inputs · Rates and valuation multiples with refresh stamps
B27: =HYPERLINK("#'Competitor Benchmarking'!A1","▸ Competitor Benchmarking · Two public comps + peer median + industry benchmarks") -> ▸ Competitor Benchmarking · Two public comps + peer median + industry benchmarks
B28: =HYPERLINK("#'Version History'!A1","▸ Version History · Audit log of every assumptions and data refresh") -> ▸ Version History · Audit log of every assumptions and data refresh
B29: =HYPERLINK("#'Sources'!A1","▸ Sources · Where every input comes from: citations, links, last-updated dates") -> ▸ Sources · Where every input comes from: citations, links, last-updated dates
B31: HOW TO USE THIS MODEL
B32: 1. Start on the Revenue Drivers and Assumptions tabs; every blue cell is an input; yellow cells are the key levers.
B33: 2. Flip the scenario selector on Regional Breakdown (1 = Standard · 2 = Best Case · 3 = Low Case); the whole model re-runs, including EPS, cash and the benchmarking tab.
B34: 3. Check Budget vs Actual for FY2025 performance vs guidance; rows over the 10% threshold flag automatically.
B35: 4. Keep market data current: run refresh_market_data.py in this folder (or use the dashboard ⟳ button); stamps update on Market Inputs and the refresh is logged in Version History.
B36: 5. For a browser walkthrough or a one-page memo, open Finance_AI_Dashboard.html and use Export memo (PDF).
B38: MODEL NOTES
B39: • FY2023–FY2025 as reported (FY2023 as revised); revenue modeled by segment (subscription + services), each with its own growth and cost ratio.
B40: • Subscription revenue is built from a customer roll-forward (CAC, churn, NRR, first-year ARPC) on the Revenue Drivers tab.
B41: • The 2025 convertible notes were repaid at maturity; the forecast carries no debt. Balance sheet balances in all periods under every scenario.
B43: COLOR CONVENTIONS
B44: Blue = hardcoded input (historical figures as reported; forecast assumptions)
... B48: Every data input is cited on the Sources tab, with links and last-updated dates.

Sheet Assumptions
A1: HubSpot, Inc.; Forecast Assumptions
A2: (USD in thousands, except per-share amounts) · FY2023A–FY2025A per SEC filings · FY2026E–FY2030E forecast
B3: FY2023A | C3: FY2024A | D3: FY2025A | E3: FY2026E | F3: FY2027E | G3: FY2028E | H3: FY2029E | I3: FY2030E
A4: Income statement drivers
A5: Subscription revenue growth %; OUTPUT (driven by Revenue Drivers tab) | C5: ='Income Statement'!C5/'Income Statement'!B5-1 -> 0.21006424 | D5: ='Income Statement'!D5/'Income Statement'!C5-1 -> 0.19239624 | E5: ='Income Statement'!E5/'Income Statement'!D5-1 -> 0.18638533 | F5: ='Income Statement'!F5/'Income Statement'!E5-1 -> 0.18212973 | G5: ='Income Statement'!G5/'Income Statement'!F5-1 -> 0.17825608 | H5: ='Income Statement'!H5/'Income Statement'!G5-1 -> 0.17455614 | I5: ='Income Statement'!I5/'Income Statement'!H5-1 -> 0.17100953 | K5: Seat + AI-credit expansion moderates from FY25's 19.2%
A6: Services & other revenue growth % | C6: ='Income Statement'!C6/'Income Statement'!B6-1 -> 0.240551 | D6: ='Income Statement'!D6/'Income Statement'!C6-1 -> 0.16124972 | E6: 0.1 | F6: 0.1 | G6: 0.1 | H6: 0.1 | I6: 0.1
A7: Subscription cost % of subscription revenue | B7: ='Income Statement'!B9/'Income Statement'!B5 -> 0.13358974 | C7: ='Income Statement'!C9/'Income Statement'!C5 -> 0.13110409 | D7: ='Income Statement'!D9/'Income Statement'!D5 -> 0.14534858 | E7: 0.145 | F7: 0.143 | G7: 0.141 | H7: 0.139 | I7: 0.137 | K7: Hosting/AI inference costs offset by infrastructure efficiency
A8: Services cost % of services revenue | B8: ='Income Statement'!B10/'Income Statement'!B6 -> 1.1697504 | C8: ='Income Statement'!C10/'Income Statement'!C6 -> 0.97223994 | D8: ='Income Statement'!D10/'Income Statement'!D6 -> 0.93766797 | E8: 0.93 | F8: 0.93 | G8: 0.93 | H8: 0.93 | I8: 0.93
A9: Research & development % of revenue | B9: ='Income Statement'!B15/'Income Statement'!B7 -> 0.28464495 | C9: ='Income Statement'!C15/'Income Statement'!C7 -> 0.29636584 | D9: ='Income Statement'!D15/'Income Statement'!D7 -> 0.28932164 | E9: 0.285 | F9: 0.28 | G9: 0.275 | H9: 0.27 | I9: 0.265
A10: Sales & marketing % of revenue | B10: ='Income Statement'!B16/'Income Statement'!B7 -> 0.49237178 | C10: ='Income Statement'!C16/'Income Statement'!C7 -> 0.46387214 | D10: ='Income Statement'!D16/'Income Statement'!D7 -> 0.44051703 | E10: 0.43 | F10: 0.42 | G10: 0.41 | H10: 0.4 | I10: 0.39 | K10: Gradual leverage from FY25's 44.0%
A11: General & administrative % of revenue | B11: ='Income Statement'!B17/'Income Statement'!B7 -> 0.11503343 | C11: ='Income Statement'!C17/'Income Statement'!C7 -> 0.11430146 | D11: ='Income Statement'!D17/'Income Statement'!D7 -> 0.10412562 | E11: 0.102 | F11: 0.1 | G11: 0.098 | H11: 0.096 | I11: 0.094
A12: Stock-based compensation % of revenue | B12: ='Cash Flow'!B7/'Income Statement'!B7 -> 0.19918211 | C12: ='Cash Flow'!C7/'Income Statement'!C7 -> 0.19210723 | D12: ='Cash Flow'!D7/'Income Statement'!D7 -> 0.16867075 | E12: 0.16 | F12: 0.152 | G12: 0.145 | H12: 0.14 | I12: 0.135
A13: Depreciation (PP&E) % of revenue | E13: 0.008 | F13: 0.008 | G13: 0.008 | H13: 0.008 | I13: 0.008
A14: Amortization of capitalized software % of revenue | E14: 0.023 | F14: 0.023 | G14: 0.023 | H14: 0.023 | I14: 0.023
A15: Effective tax rate % | C15: ='Income Statement'!C26/'Income Statement'!C25 -> 0.83861631 | D15: ='Income Statement'!D26/'Income Statement'!D25 -> 0.3390582 | E15: 0.3 | F15: 0.28 | G15: 0.27 | H15: 0.26 | I15: 0.25 | K15: FY23 rate not meaningful (pre-tax loss); normalizes as profitability scales
A16: Interest yield on beginning cash & investments % | C16: ='Income Statement'!C22/('Balance Sheet'!B5+'Balance Sheet'!B6+'Balance Sheet'!B11) -> 0.048255039 | D16: ='Income Statement'!D22/('Balance Sheet'!C5+'Balance Sheet'!C6+'Balance Sheet'!C11) -> 0.029778204 | E16: 0.035 | F16: 0.035 | G16: 0.035 | H16: 0.035 | I16: 0.035
A17: Diluted share count growth % | C17: ='Income Statement'!C29/'Income Statement'!B29-1 -> 0.038935782 | D17: ='Income Statement'!D29/'Income Statement'!C29-1 -> 0.026534669 | E17: 0.01 | F17: 0.01 | G17: 0.01 | H17: 0.01 | I17: 0.01
A19: Balance sheet drivers
A20: Accounts receivable · days sales outstanding | B20: ='Balance Sheet'!B7/'Income Statement'!B7*365 -> 49.665517 | C20: ='Balance Sheet'!C7/'Income Statement'!C7*365 -> 46.512116 | D20: ='Balance Sheet'!D7/'Income Statement'!D7*365 -> 48.858286 | E20: 49 | F20: 49 | G20: 48 | H20: 48 | I20: 47
A21: Deferred commissions (current) % of revenue | B21: ='Balance Sheet'!B8/'Income Statement'!B7 -> 0.045767499 | C21: ='Balance Sheet'!C8/'Income Statement'!C7 -> 0.05659013 | D21: ='Balance Sheet'!D8/'Income Statement'!D7 -> 0.072234042 | E21: 0.072 | F21: 0.072 | G21: 0.072 | H21: 0.072 | I21: 0.072
A22: Deferred commissions (noncurrent) % of revenue | B22: ='Balance Sheet'!B15/'Income Statement'!B7 -> 0.056304631 | C22: ='Balance Sheet'!C15/'Income Statement'!C7 -> 0.061203185 | D22: ='Balance Sheet'!D15/'Income Statement'!D7 -> 0.069936888 | E22: 0.07 | F22: 0.07 | G22: 0.07 | H22: 0.07 | I22: 0.07
A23: Prepaid & other current assets % of revenue | B23: ='Balance Sheet'!B9/'Income Statement'!B7 -> 0.040861568 | C23: ='Balance Sheet'!C9/'Income Statement'!C7 -> 0.030669717 | D23: ='Balance Sheet'!D9/'Income Statement'!D7 -> 0.032131093 | E23: 0.032 | F23: 0.032 | G23: 0.032 | H23: 0.032 | I23: 0.032
A24: Other assets % of revenue | B24: ='Balance Sheet'!B16/'Income Statement'!B7 -> 0.034672362 | C24: ='Balance Sheet'!C16/'Income Statement'!C7 -> 0.043863792 | D24: ='Balance Sheet'!D16/'Income Statement'!D7 -> 0.052886596 | E24: 0.053 | F24: 0.053 | G24: 0.053 | H24: 0.053 | I24: 0.053
A25: Accounts payable % of revenue | B25: ='Balance Sheet'!B22/'Income Statement'!B7 -> 0.0041958686 | C25: ='Balance Sheet'!C22/'Income Statement'!C7 -> 0.0013887499 | D25: ='Balance Sheet'!D22/'Income Statement'!D7 -> 0.0079086223 | E25: 0.006 | F25: 0.006 | G25: 0.006 | H25: 0.006 | I25: 0.006
A26: Accrued compensation % of revenue | B26: ='Balance Sheet'!B23/'Income Statement'!B7 -> 0.024634255 | C26: ='Balance Sheet'!C23/'Income Statement'!C7 -> 0.025667325 | D26: ='Balance Sheet'!D23/'Income Statement'!D7 -> 0.03167888 | E26: 0.032 | F26: 0.032 | G26: 0.032 | H26: 0.032 | I26: 0.032
A27: Accrued commissions % of revenue | B27: ='Balance Sheet'!B24/'Income Statement'!B7 -> 0.036018763 | C27: ='Balance Sheet'!C24/'Income Statement'!C7 -> 0.038835901 | D27: ='Balance Sheet'!D24/'Income Statement'!D7 -> 0.042156431 | E27: 0.042 | F27: 0.042 | G27: 0.042 | H27: 0.042 | I27: 0.042
A28: Accrued expenses & other % of revenue | B28: ='Balance Sheet'!B25/'Income Statement'!B7 -> 0.043347479 | C28: ='Balance Sheet'!C25/'Income Statement'!C7 -> 0.04762434 | D28: ='Balance Sheet'!D25/'Income Statement'!D7 -> 0.05328867 | E28: 0.052 | F28: 0.052 | G28: 0.052 | H28: 0.052 | I28: 0.052
A29: Deferred revenue (current) % of revenue | B29: ='Balance Sheet'!B28/'Income Statement'!B7 -> 0.30971372 | C29: ='Balance Sheet'!C28/'Income Statement'!C7 -> 0.2984739 | D29: ='Balance Sheet'!D28/'Income Statement'!D7 -> 0.32093888 | E29: 0.325 | F29: 0.328 | G29: 0.33 | H29: 0.332 | I29: 0.334 | K29: Billings mix shifts modestly toward annual prepay
A30: Deferred revenue (noncurrent) % of revenue | B30: ='Balance Sheet'!B31/'Income Statement'!B7 -> 0.0026771356 | C30: ='Balance Sheet'!C31/'Income Statement'!C7 -> 0.0015105366 | D30: ='Balance Sheet'!D31/'Income Statement'!D7 -> 0.0027129602 | E30: 0.003 | F30: 0.003 | G30: 0.003 | H30: 0.003 | I30: 0.003
A31: Capital expenditures % of revenue | B31: =-'Cash Flow'!B19/'Income Statement'!B7 -> 0.015536602 | C31: =-'Cash Flow'!C19/'Income Statement'!C7 -> 0.014438964 | D31: =-'Cash Flow'!D19/'Income Statement'!D7 -> 0.016978756 | E31: 0.017 | F31: 0.017 | G31: 0.017 | H31: 0.017 | I31: 0.017
A32: Capitalized software additions % of revenue | B32: =-'Cash Flow'!B20/'Income Statement'!B7 -> 0.030582934 | C32: =-'Cash Flow'!C20/'Income Statement'!C7 -> 0.034113999 | D32: =-'Cash Flow'!D20/'Income Statement'!D7 -> 0.041716034 | E32: 0.042 | F32: 0.042 | G32: 0.042 | H32: 0.042 | I32: 0.042
A34: Financing drivers ($000s)
A35: Share repurchases | B35: =-'Cash Flow'!B28 -> 0 | C35: =-'Cash Flow'!C28 -> 0 | D35: =-'Cash Flow'!D28 -> 500019 | E35: 450000 | F35: 450000 | G35: 500000 | H35: 500000 | I35: 550000 | K35: FY25 actual: $500m buyback
A36: Proceeds from stock plans | B36: ='Cash Flow'!B27 -> 47738 | C36: ='Cash Flow'!C27 -> 75501 | D36: ='Cash Flow'!D27 -> 71394 | E36: 75000 | F36: 75000 | G36: 75000 | H36: 75000 | I36: 75000
A37: Employee taxes on net share settlement | B37: =-'Cash Flow'!B30 -> 10714 | C37: =-'Cash Flow'!C30 -> 21949 | D37: =-'Cash Flow'!D30 -> 21573 | E37: 25000 | F37: 25000 | G37: 25000 | H37: 25000 | I37: 25000
A39: Historical columns compute actual ratios from the statement tabs; forecast columns (blue) are inputs.
A40: Investments, leases, goodwill and intangibles held flat in the forecast; 2025 convertible notes were repaid at maturity.

Sheet Revenue Drivers
A1: HubSpot, Inc.; Revenue Drivers (SaaS)
A2: SaaS unit-economics build (USD in thousands unless noted) · drives Subscription revenue on the Income Statement
B3: FY2023A | C3: FY2024A | D3: FY2025A | E3: FY2026E | F3: FY2027E | G3: FY2028E | H3: FY2029E | I3: FY2030E
A4: Customer roll-forward
A5: Customers, beginning of period | C5: =B8 -> 205091 | D5: =C8 -> 247939 | E5: =D8 -> 288706 | F5: =E8 -> 339694.01 | G5: =F8 -> 394330.17 | H5: =G8 -> 455066.63 | I5: =H8 -> 520425.93
A6: New customers added (new-business S&M ÷ CAC) | E6: =E15/E13 -> 79858.611 | F6: =F15/F13 -> 88605.563 | G6: =G15/G13 -> 98197.82 | H6: =H15/H13 -> 108590.63 | I6: =I15/I13 -> 119818.32
A7: Less: customers churned | E7: =E5*E12 -> 28870.6 | F7: =F5*F12 -> 33969.401 | G7: =G5*G12 -> 37461.366 | H7: =H5*H12 -> 43231.329 | I7: =I5*I12 -> 46838.334
A8: Customers · end of period | B8: 205091 | C8: 247939 | D8: 288706 | E8: =E5+E6-E7 -> 339694.01 | F8: =F5+F6-F7 -> 394330.17 | G8: =G5+G6-G7 -> 455066.63 | H8: =H5+H6-H7 -> 520425.93 | I8: =I5+I6-I7 -> 593405.92
A9: Average customers | B9: =B8 -> 205091 | C9: =(C5+C8)/2 -> 226515 | D9: =(D5+D8)/2 -> 268322.5 | E9: =(E5+E8)/2 -> 314200.01 | F9: =(F5+F8)/2 -> 367012.09 | G9: =(G5+G8)/2 -> 424698.4 | H9: =(H5+H8)/2 -> 487746.28 | I9: =(I5+I8)/2 -> 556915.92
A11: Unit economics (inputs)
A12: Annual logo churn rate % | E12: 0.1 | F12: 0.1 | G12: 0.095 | H12: 0.095 | I12: 0.09
A13: Customer acquisition cost · CAC ($000s / customer) | E13: 9.5 | F13: 9.9 | G13: 10.3 | H13: 10.7 | I13: 11.1
A14: % of prior-year S&M deployed on new business | E14: 0.55 | F14: 0.55 | G14: 0.55 | H14: 0.55 | I14: 0.55
A15: New-business S&M budget ($000s, lagged one year) | E15: ='Income Statement'!D16*E14 -> 758656.8 | F15: ='Income Statement'!E16*F14 -> 877195.07 | G15: ='Income Statement'!F16*G14 -> 1011437.5 | H15: ='Income Statement'!G16*H14 -> 1161919.8 | I15: ='Income Statement'!H16*I14 -> 1329983.3
A16: First-year ARPC · new customers ($000s) | E16: 6 | F16: 6.2 | G16: 6.4 | H16: 6.6 | I16: 6.8
A17: Net revenue retention (NRR) % | C17: 1.018 | D17: 1.035 | E17: 1.03 | F17: 1.031 | G17: 1.032 | H17: 1.033 | I17: 1.034
A19: Subscription revenue build ($000s)
A20: Retained + expansion revenue (prior revenue × NRR) | E20: =D22*E17 -> 3155834.5 | F20: =E22*F17 -> 3747670.7 | G20: =F22*G17 -> 4434530 | H20: =G22*H17 -> 5230075 | I20: =H22*I17 -> 6148963.4
A21: New-business revenue (gross adds × first-year ARPC) | E21: =E6*E16 -> 479151.66 | F21: =F6*F16 -> 549354.49 | G21: =G6*G16 -> 628466.05 | H21: =H6*H16 -> 716698.18 | I21: =I6*I16 -> 814764.57
A22: SUBSCRIPTION REVENUE ($000s) | B22: 2123479 | C22: 2569546 | D22: 3063917 | E22: =E20+E21 -> 3634986.2 | F22: =F20+F21 -> 4297025.2 | G22: =G20+G21 -> 5062996.1 | H22: =H20+H21 -> 5946773.1 | I22: =I20+I21 -> 6963728
A23: Check vs Income Statement (must be 0) | B23: =B22-'Income Statement'!B5 -> 0 | C23: =C22-'Income Statement'!C5 -> 0 | D23: =D22-'Income Statement'!D5 -> 0 | E23: =E22*'Regional Breakdown'!E41-'Income Statement'!E5 -> 0 | F23: =F22*'Regional Breakdown'!F41-'Income Statement'!F5 -> 0 | G23: =G22*'Regional Breakdown'!G41-'Income Statement'!G5 -> 0 | H23: =H22*'Regional Breakdown'!H41-'Income Statement'!H5 -> 0 | I23: =I22*'Regional Breakdown'!I41-'Income Statement'!I5 -> 0
A25: KPIs (computed)
A26: Implied ARPC on average customers ($ / yr) | B26: =B22/B9*1000 -> 10353.838 | C26: =C22/C9*1000 -> 11343.823 | D26: =D22/D9*1000 -> 11418.785 | E26: =E22/E9*1000 -> 11569.02 | F26: =F22/F9*1000 -> 11708.13 | G26: =G22/G9*1000 -> 11921.392 | H26: =H22/H9*1000 -> 12192.35 | I26: =I22/I9*1000 -> 12504.092
A27: Implied ending MRR ($000s / month) | B27: =B22/12 -> 176956.58 | C27: =C22/12 -> 214128.83 | D27: =D22/12 -> 255326.42 | E27: =E22/12 -> 302915.51 | F27: =F22/12 -> 358085.44 | G27: =G22/12 -> 421916.34 | H27: =H22/12 -> 495564.43 | I27: =I22/12 -> 580310.67
A28: CAC payback (months, on subscription gross margin) | E28: =E13/(E16*(1-Assumptions!E7))*12 -> 22.222222 | F28: =F13/(F16*(1-Assumptions!F7))*12 -> 22.358565 | G28: =G13/(G16*(1-Assumptions!G7))*12 -> 22.482538 | H28: =H13/(H16*(1-Assumptions!H7))*12 -> 22.595291 | I28: =I13/(I16*(1-Assumptions!I7))*12 -> 22.697839
A29: LTV / CAC (x) | E29: =(E26/1000*(1-Assumptions!E7)/E12)/E13 -> 10.412118 | F29: =(F26/1000*(1-Assumptions!F7)/F12)/F13 -> 10.13522 | G29: =(G26/1000*(1-Assumptions!G7)/G12)/G13 -> 10.465484 | H29: =(H26/1000*(1-Assumptions!H7)/H12)/H13 -> 10.327214 | I29: =(I26/1000*(1-Assumptions!I7)/I12)/I13 -> 10.801833
A31: Customer counts, ARPC and NRR per company disclosures (Q4 releases and earnings calls); FY25 NRR ~103.5%, exiting at 105%.
A32: New adds are funded from PRIOR-year S&M (lagged) to avoid a circular reference with current-year revenue.
A33: CAC and churn are blended estimates (not company-disclosed); flex the blue inputs to test unit-economics scenarios.

Sheet Regional Breakdown
A1: HubSpot, Inc.; Regional Breakdown & Scenarios
A2: Revenue, growth and customers by region (USD in thousands unless noted) · regional scenario toggle feeds the Income Statement · base = total revenue
B3: FY2023A | C3: FY2024A | D3: FY2025A | E3: FY2026E | F3: FY2027E | G3: FY2028E | H3: FY2029E | I3: FY2030E
A4: SCENARIO SELECTOR (1 = Standard · 2 = Best Case · 3 = Low Case) | B4: 1 | C4: =CHOOSE(B4,"STANDARD CASE","BEST CASE","LOW CASE") -> STANDARD CASE
A6: REGIONAL MIX (% of total revenue)
A7: North America mix % | B7: 0.609 | C7: 0.605 | D7: 0.598 | E7: 0.595 | F7: 0.592 | G7: 0.589 | H7: 0.586 | I7: 0.583
A8: Europe mix % | B8: 0.308 | C8: 0.314 | D8: 0.323 | E8: 0.325 | F8: 0.327 | G8: 0.329 | H8: 0.331 | I8: 0.333
A9: Asia Pacific mix % | B9: 0.083 | C9: 0.081 | D9: 0.079 | E9: 0.08 | F9: 0.081 | G9: 0.082 | H9: 0.083 | I9: 0.084
A10: Other / rest of world mix % (balancing) | B10: =1-B7-B8-B9 -> 0 | C10: =1-C7-C8-C9 -> 0 | D10: =1-D7-D8-D9 -> 0 | E10: =1-E7-E8-E9 -> 0 | F10: =1-F7-F8-F9 -> 0 | G10: =1-G7-G8-G9 -> 0 | H10: =1-H7-H8-H9 -> 0 | I10: =1-I7-I8-I9 -> 0
A12: BASE TOTAL REVENUE BY REGION ($000s)
A13: Professional services & other revenue · base path | B13: ='Income Statement'!B6 -> 46751 | C13: ='Income Statement'!C6 -> 57997 | D13: ='Income Statement'!D6 -> 67349 | E13: =D13*(1+Assumptions!E6) -> 74083.9 | F13: =E13*(1+Assumptions!F6) -> 81492.29 | G13: =F13*(1+Assumptions!G6) -> 89641.519 | H13: =G13*(1+Assumptions!H6) -> 98605.671 | I13: =H13*(1+Assumptions!I6) -> 108466.24
A14: Base total revenue before regional split | B14: ='Revenue Drivers'!B22+B13 -> 2170230 | C14: ='Revenue Drivers'!C22+C13 -> 2627543 | D14: ='Revenue Drivers'!D22+D13 -> 3131266 | E14: ='Revenue Drivers'!E22+E13 -> 3709070.1 | F14: ='Revenue Drivers'!F22+F13 -> 4378517.5 | G14: ='Revenue Drivers'!G22+G13 -> 5152637.6 | H14: ='Revenue Drivers'!H22+H13 -> 6045378.8 | I14: ='Revenue Drivers'!I22+I13 -> 7072194.2
A15: North America · base | B15: =B14*B7 -> 1321670.1 | C15: =C14*C7 -> 1589663.5 | D15: =D14*D7 -> 1872497.1 | E15: =E14*E7 -> 2206896.7 | F15: =F14*F7 -> 2592082.4 | G15: =G14*G7 -> 3034903.6 | H15: =H14*H7 -> 3542592 | I15: =I14*I7 -> 4123089.2
A16: Europe · base | B16: =B14*B8 -> 668430.84 | C16: =C14*C8 -> 825048.5 | D16: =D14*D8 -> 1011398.9 | E16: =E14*E8 -> 1205447.8 | F16: =F14*F8 -> 1431775.2 | G16: =G14*G8 -> 1695217.8 | H16: =H14*H8 -> 2001020.4 | I16: =I14*I8 -> 2355040.7
A17: Asia Pacific · base | B17: =B14*B9 -> 180129.09 | C17: =C14*C9 -> 212830.98 | D17: =D14*D9 -> 247370.01 | E17: =E14*E9 -> 296725.61 | F17: =F14*F9 -> 354659.92 | G17: =G14*G9 -> 422516.28 | H17: =H14*H9 -> 501766.44 | I17: =I14*I9 -> 594064.32
A18: Other / rest of world · base | B18: =B14*B10 -> 0 | C18: =C14*C10 -> 0 | D18: =D14*D10 -> 0 | E18: =E14*E10 -> 0 | F18: =F14*F10 -> 0 | G18: =G14*G10 -> 0 | H18: =H14*H10 -> 0 | I18: =I14*I10 -> 0
A19: Total base (sum of regions) | B19: =SUM(B15:B18) -> 2170230 | C19: =SUM(C15:C18) -> 2627543 | D19: =SUM(D15:D18) -> 3131266 | E19: =SUM(E15:E18) -> 3709070.1 | F19: =SUM(F15:F18) -> 4378517.5 | G19: =SUM(G15:G18) -> 5152637.6 | H19: =SUM(H15:H18) -> 6045378.8 | I19: =SUM(I15:I18) -> 7072194.2
A21: BASE REGIONAL GROWTH %
A22: North America growth % | C22: =C15/B15-1 -> 0.20276879 | D22: =D15/C15-1 -> 0.17792039 | E22: =E15/D15-1 -> 0.17858486 | F22: =F15/E15-1 -> 0.17453725 | G22: =G15/F15-1 -> 0.17083607 | H22: =H15/G15-1 -> 0.16728322 | I22: =I15/H15-1 -> 0.1638623
A23: Europe growth % | C23: =C16/B16-1 -> 0.23430646 | D23: =D16/C16-1 -> 0.22586601 | E23: =E16/D16-1 -> 0.19186184 | F23: =F16/E16-1 -> 0.18775385 | G23: =G16/F16-1 -> 0.18399714 | H23: =H16/G16-1 -> 0.18039135 | I23: =I16/H16-1 -> 0.17691988
A24: Asia Pacific growth % | C24: =C17/B17-1 -> 0.18154698 | D24: =D17/C17-1 -> 0.16228385 | E24: =E17/D17-1 -> 0.19952132 | F24: =F17/E17-1 -> 0.19524541 | G24: =G17/F17-1 -> 0.19132798 | H24: =H17/G17-1 -> 0.18756711 | I24: =I17/H17-1 -> 0.18394589
A26: SCENARIO GROWTH DELTAS (added to base regional growth)
A27: Best Case · North America | E27: 0.02 | F27: 0.02 | G27: 0.02 | H27: 0.02 | I27: 0.02
A28: Best Case · Europe | E28: 0.03 | F28: 0.03 | G28: 0.03 | H28: 0.03 | I28: 0.03
A29: Best Case · Asia Pacific | E29: 0.05 | F29: 0.05 | G29: 0.05 | H29: 0.05 | I29: 0.05
A30: Low Case · North America | E30: -0.03 | F30: -0.03 | G30: -0.03 | H30: -0.03 | I30: -0.03
A31: Low Case · Europe | E31: -0.045 | F31: -0.045 | G31: -0.045 | H31: -0.045 | I31: -0.045
A32: Low Case · Asia Pacific | E32: -0.06 | F32: -0.06 | G32: -0.06 | H32: -0.06 | I32: -0.06
A34: SCENARIO TOTAL REVENUE BY REGION ($000s)
A35: North America · scenario | B35: =B15 -> 1321670.1 | C35: =C15 -> 1589663.5 | D35: =D15 -> 1872497.1 | E35: =D35*(1+E22+CHOOSE($B$4,0,E27,E30)) -> 2206896.7 | F35: =E35*(1+F22+CHOOSE($B$4,0,F27,F30)) -> 2592082.4 | G35: =F35*(1+G22+CHOOSE($B$4,0,G27,G30)) -> 3034903.6 | H35: =G35*(1+H22+CHOOSE($B$4,0,H27,H30)) -> 3542592 | I35: =H35*(1+I22+CHOOSE($B$4,0,I27,I30)) -> 4123089.2
A36: Europe · scenario | B36: =B16 -> 668430.84 | C36: =C16 -> 825048.5 | D36: =D16 -> 1011398.9 | E36: =D36*(1+E23+CHOOSE($B$4,0,E28,E31)) -> 1205447.8 | F36: =E36*(1+F23+CHOOSE($B$4,0,F28,F31)) -> 1431775.2 | G36: =F36*(1+G23+CHOOSE($B$4,0,G28,G31)) -> 1695217.8 | H36: =G36*(1+H23+CHOOSE($B$4,0,H28,H31)) -> 2001020.4 | I36: =H36*(1+I23+CHOOSE($B$4,0,I28,I31)) -> 2355040.7
A37: Asia Pacific · scenario | B37: =B17 -> 180129.09 | C37: =C17 -> 212830.98 | D37: =D17 -> 247370.01 | E37: =D37*(1+E24+CHOOSE($B$4,0,E29,E32)) -> 296725.61 | F37: =E37*(1+F24+CHOOSE($B$4,0,F29,F32)) -> 354659.92 | G37: =F37*(1+G24+CHOOSE($B$4,0,G29,G32)) -> 422516.28 | H37: =G37*(1+H24+CHOOSE($B$4,0,H29,H32)) -> 501766.44 | I37: =H37*(1+I24+CHOOSE($B$4,0,I29,I32)) -> 594064.32
A38: Other / rest of world · scenario (no delta) | B38: =B18 -> 0 | C38: =C18 -> 0 | D38: =D18 -> 0 | E38: =E18 -> 0 | F38: =F18 -> 0 | G38: =G18 -> 0 | H38: =H18 -> 0 | I38: =I18 -> 0
A39: TOTAL · SCENARIO ($000s) | B39: =SUM(B35:B38) -> 2170230 | C39: =SUM(C35:C38) -> 2627543 | D39: =SUM(D35:D38) -> 3131266 | E39: =SUM(E35:E38) -> 3709070.1 | F39: =SUM(F35:F38) -> 4378517.5 | G39: =SUM(G35:G38) -> 5152637.6 | H39: =SUM(H35:H38) -> 6045378.8 | I39: =SUM(I35:I38) -> 7072194.2
A40: Scenario total growth % | C40: =C39/B39-1 -> 0.21072098 | D40: =D39/C39-1 -> 0.19170876 | E40: =E39/D39-1 -> 0.1845273 | F40: =F39/E39-1 -> 0.1804893 | G40: =G39/F39-1 -> 0.17679959 | H40: =H39/G39-1 -> 0.17325907 | I40: =I39/H39-1 -> 0.1698513
A41: Scenario scaling factor (× base) | B41: =B39/B19 -> 1 | C41: =C39/C19 -> 1 | D41: =D39/D19 -> 1 | E41: =E39/E19 -> 1 | F41: =F39/F19 -> 1 | G41: =G39/G19 -> 1 | H41: =H39/H19 -> 1 | I41: =I39/I19 -> 1
A42: Scenario revenue delta vs base ($000s) | B42: =B39-B19 -> 0 | C42: =C39-C19 -> 0 | D42: =D39-D19 -> 0 | E42: =E39-E19 -> 0 | F42: =F39-F19 -> 0 | G42: =G39-G19 -> 0 | H42: =H39-H19 -> 0 | I42: =I39-I19 -> 0
A44: SCENARIO IMPACT DASHBOARD (flips with the selector)
A45: Net income · scenario ($000s) | B45: ='Income Statement'!B27 -> -164510 | C45: ='Income Statement'!C27 -> 4628 | D45: ='Income Statement'!D27 -> 45911 | E45: ='Income Statement'!E27 -> 103043.33 | F45: ='Income Statement'!F27 -> 186277.57 | G45: ='Income Statement'!G27 -> 298166.43 | H45: ='Income Statement'!H27 -> 446431.16 | I45: ='Income Statement'!I27 -> 640883.62
A46: Diluted EPS · scenario ($) | B46: ='Income Statement'!B30 -> -3.2983139 | C46: ='Income Statement'!C30 -> 0.089310871 | D46: ='Income Statement'!D30 -> 0.86308606 | E46: ='Income Statement'!E30 -> 1.9179438 | F46: ='Income Statement'!F30 -> 3.4328527 | G46: ='Income Statement'!G30 -> 5.4404144 | H46: ='Income Statement'!H30 -> 8.0650368 | I46: ='Income Statement'!I30 -> 11.4633
A47: Ending cash · scenario ($000s) | B47: ='Balance Sheet'!B5 -> 387987 | C47: ='Balance Sheet'!C5 -> 512667 | D47: ='Balance Sheet'!D5 -> 882242 | E47: ='Balance Sheet'!E5 -> 1135437 | F47: ='Balance Sheet'!F5 -> 1543896.5 | G47: ='Balance Sheet'!G5 -> 2098113 | H47: ='Balance Sheet'!H5 -> 2878788.1 | I47: ='Balance Sheet'!I5 -> 3921319.2
A48: Revenue CAGR FY2025A → FY2030E (scenario) | B48: =(I39/D39)^0.2-1 -> 0.17697393
A50: CUSTOMERS BY REGION
A51: Total customers (count) | B51: ='Revenue Drivers'!B8 -> 205091 | C51: ='Revenue Drivers'!C8 -> 247939 | D51: ='Revenue Drivers'!D8 -> 288706 | E51: ='Revenue Drivers'!E8 -> 339694.01 | F51: ='Revenue Drivers'!F8 -> 394330.17 | G51: ='Revenue Drivers'!G8 -> 455066.63 | H51: ='Revenue Drivers'!H8 -> 520425.93 | I51: ='Revenue Drivers'!I8 -> 593405.92
A52: North America customer mix % | B52: 0.52 | C52: 0.51 | D52: 0.5 | E52: 0.495 | F52: 0.49 | G52: 0.485 | H52: 0.48 | I52: 0.475
A53: Europe customer mix % | B53: 0.36 | C53: 0.37 | D53: 0.375 | E53: 0.378 | F53: 0.38 | G53: 0.382 | H53: 0.384 | I53: 0.386
A54: Asia Pacific customer mix % | B54: 0.1 | C54: 0.1 | D54: 0.105 | E54: 0.107 | F54: 0.109 | G54: 0.111 | H54: 0.113 | I54: 0.115
A55: Other customer mix % (balancing) | B55: =1-B52-B53-B54 -> 0.02 | C55: =1-C52-C53-C54 -> 0.02 | D55: =1-D52-D53-D54 -> 0.02 | E55: =1-E52-E53-E54 -> 0.02 | F55: =1-F52-F53-F54 -> 0.021 | G55: =1-G52-G53-G54 -> 0.022 | H55: =1-H52-H53-H54 -> 0.023 | I55: =1-I52-I53-I54 -> 0.024
A56: North America · customers | B56: =B51*B52 -> 106647.32 | C56: =C51*C52 -> 126448.89 | D56: =D51*D52 -> 144353 | E56: =E51*E52 -> 168148.54 | F56: =F51*F52 -> 193221.78 | G56: =G51*G52 -> 220707.31 | H56: =H51*H52 -> 249804.45 | I56: =I51*I52 -> 281867.81
A57: Europe · customers | B57: =B51*B53 -> 73832.76 | C57: =C51*C53 -> 91737.43 | D57: =D51*D53 -> 108264.75 | E57: =E51*E53 -> 128404.34 | F57: =F51*F53 -> 149845.47 | G57: =G51*G53 -> 173835.45 | H57: =H51*H53 -> 199843.56 | I57: =I51*I53 -> 229054.68
A58: Asia Pacific · customers | B58: =B51*B54 -> 20509.1 | C58: =C51*C54 -> 24793.9 | D58: =D51*D54 -> 30314.13 | E58: =E51*E54 -> 36347.259 | F58: =F51*F54 -> 42981.989 | G58: =G51*G54 -> 50512.396 | H58: =H51*H54 -> 58808.13 | I58: =I51*I54 -> 68241.68
A59: Other · customers | B59: =B51*B55 -> 4101.82 | C59: =C51*C55 -> 4958.78 | D59: =D51*D55 -> 5774.12 | E59: =E51*E55 -> 6793.8802 | F59: =F51*F55 -> 8280.9336 | G59: =G51*G55 -> 10011.466 | H59: =H51*H55 -> 11969.796 | I59: =I51*I55 -> 14241.742
A61: Check: regional mix sums to 100% (must be 0) | B61: =B19-B14 -> 0 | C61: =C19-C14 -> 0 | D61: =D19-D14 -> 0 | E61: =E19-E14 -> 0 | F61: =F19-F14 -> 0 | G61: =G19-G14 -> 0 | H61: =H19-H14 -> 0 | I61: =I19-I14 -> 0
A62: Check: scenario total ties to Income Statement (must be 0) | B62: =B39-'Income Statement'!B7 -> 0 | C62: =C39-'Income Statement'!C7 -> 0 | D62: =D39-'Income Statement'!D7 -> 0 | E62: =E39-'Income Statement'!E7 -> 0 | F62: =F39-'Income Statement'!F7 -> 0 | G62: =G39-'Income Statement'!G7 -> 0 | H62: =H39-'Income Statement'!H7 -> 0 | I62: =I39-'Income Statement'!I7 -> 0
A64: • Regional revenue mix per the 10-K geographic disclosure (Americas / Europe / Asia Pacific); ~40% of revenue is generated outside the Americas.
A65: • The scenario scaling factor multiplies both subscription and services revenue on the Income Statement, so all downstream statements flex with the toggle. New-customer adds also respond (they are funded from prior-year S&M).
A66: • Customer regional mix is an estimate; HubSpot discloses customer counts in total (288,706 at FY25) but not by region; international customers skew higher than revenue mix due to lower ARPC.

Sheet Income Statement
A1: HubSpot, Inc.; Income Statement
A2: (USD in thousands, except per-share amounts) · FY2023A–FY2025A per SEC filings · FY2026E–FY2030E forecast
B3: FY2023A | C3: FY2024A | D3: FY2025A | E3: FY2026E | F3: FY2027E | G3: FY2028E | H3: FY2029E | I3: FY2030E
A4: Revenue
A5: Subscription | B5: 2123479 | C5: 2569546 | D5: 3063917 | E5: ='Revenue Drivers'!E22*'Regional Breakdown'!E41 -> 3634986.2 | F5: ='Revenue Drivers'!F22*'Regional Breakdown'!F41 -> 4297025.2 | G5: ='Revenue Drivers'!G22*'Regional Breakdown'!G41 -> 5062996.1 | H5: ='Revenue Drivers'!H22*'Regional Breakdown'!H41 -> 5946773.1 | I5: ='Revenue Drivers'!I22*'Regional Breakdown'!I41 -> 6963728 | K5: Source: HUBS Q4 FY2025 and Q4 FY2024 earnings releases (SEC 8-K Ex. 99.1); FY2023 as revised
A6: Professional services and other | B6: 46751 | C6: 57997 | D6: 67349 | E6: ='Regional Breakdown'!E13*'Regional Breakdown'!E41 -> 74083.9 | F6: ='Regional Breakdown'!F13*'Regional Breakdown'!F41 -> 81492.29 | G6: ='Regional Breakdown'!G13*'Regional Breakdown'!G41 -> 89641.519 | H6: ='Regional Breakdown'!H13*'Regional Breakdown'!H41 -> 98605.671 | I6: ='Regional Breakdown'!I13*'Regional Breakdown'!I41 -> 108466.24
A7: Total revenue | B7: =B5+B6 -> 2170230 | C7: =C5+C6 -> 2627543 | D7: =D5+D6 -> 3131266 | E7: =E5+E6 -> 3709070.1 | F7: =F5+F6 -> 4378517.5 | G7: =G5+G6 -> 5152637.6 | H7: =H5+H6 -> 6045378.8 | I7: =I5+I6 -> 7072194.2
A8: Cost of revenue
A9: Cost of revenue · subscription | B9: 283675 | C9: 336878 | D9: 445336 | E9: =E5*Assumptions!E7 -> 527073 | F9: =F5*Assumptions!F7 -> 614474.61 | G9: =G5*Assumptions!G7 -> 713882.45 | H9: =H5*Assumptions!H7 -> 826601.47 | I9: =I5*Assumptions!I7 -> 954030.74
A10: Cost of revenue · professional services and other | B10: 54687 | C10: 56387 | D10: 63151 | E10: =E6*Assumptions!E8 -> 68898.027 | F10: =F6*Assumptions!F8 -> 75787.83 | G10: =G6*Assumptions!G8 -> 83366.613 | H10: =H6*Assumptions!H8 -> 91703.274 | I10: =I6*Assumptions!I8 -> 100873.6
A11: Total cost of revenue | B11: =B9+B10 -> 338362 | C11: =C9+C10 -> 393265 | D11: =D9+D10 -> 508487 | E11: =E9+E10 -> 595971.02 | F11: =F9+F10 -> 690262.44 | G11: =G9+G10 -> 797249.06 | H11: =H9+H10 -> 918304.74 | I11: =I9+I10 -> 1054904.3
A12: Gross profit | B12: =B7-B11 -> 1831868 | C12: =C7-C11 -> 2234278 | D12: =D7-D11 -> 2622779 | E12: =E7-E11 -> 3113099.1 | F12: =F7-F11 -> 3688255.1 | G12: =G7-G11 -> 4355388.5 | H12: =H7-H11 -> 5127074.1 | I12: =I7-I11 -> 6017289.9
A14: Operating expenses
A15: Research and development | B15: 617745 | C15: 778714 | D15: 905943 | E15: =E7*Assumptions!E9 -> 1057085 | F15: =F7*Assumptions!F9 -> 1225984.9 | G15: =G7*Assumptions!G9 -> 1416975.3 | H15: =H7*Assumptions!H9 -> 1632252.3 | I15: =I7*Assumptions!I9 -> 1874131.5
A16: Sales and marketing | B16: 1068560 | C16: 1218844 | D16: 1379376 | E16: =E7*Assumptions!E10 -> 1594900.1 | F16: =F7*Assumptions!F10 -> 1838977.4 | G16: =G7*Assumptions!G10 -> 2112581.4 | H16: =H7*Assumptions!H10 -> 2418151.5 | I16: =I7*Assumptions!I10 -> 2758155.8
A17: General and administrative | B17: 249649 | C17: 300332 | D17: 326045 | E17: =E7*Assumptions!E11 -> 378325.15 | F17: =F7*Assumptions!F11 -> 437851.75 | G17: =G7*Assumptions!G11 -> 504958.49 | H17: =H7*Assumptions!H11 -> 580356.37 | I17: =I7*Assumptions!I11 -> 664786.26
A18: Restructuring | B18: 96843 | C18: 3990 | D18: 4036 | E18: 0 | F18: 0 | G18: 0 | H18: 0 | I18: 0
A19: Total operating expenses | B19: =SUM(B15:B18) -> 2032797 | C19: =SUM(C15:C18) -> 2301880 | D19: =SUM(D15:D18) -> 2615400 | E19: =SUM(E15:E18) -> 3030310.2 | F19: =SUM(F15:F18) -> 3502814 | G19: =SUM(G15:G18) -> 4034515.2 | H19: =SUM(H15:H18) -> 4630760.2 | I19: =SUM(I15:I18) -> 5297073.5
A20: Income (loss) from operations | B20: =B12-B19 -> -200929 | C20: =C12-C19 -> -67602 | D20: =D12-D19 -> 7379 | E20: =E12-E19 -> 82788.801 | F20: =F12-F19 -> 185441.07 | G20: =G12-G19 -> 320873.3 | H20: =H12-H19 -> 496313.9 | I20: =I12-I19 -> 720216.42
A22: Interest income | B22: 58828 | C22: 82706 | D22: 66218 | E22: =('Balance Sheet'!D5+'Balance Sheet'!D6+'Balance Sheet'!D11)*Assumptions!E16 -> 64415.96 | F22: =('Balance Sheet'!E5+'Balance Sheet'!E6+'Balance Sheet'!E11)*Assumptions!F16 -> 73277.783 | G22: =('Balance Sheet'!F5+'Balance Sheet'!F6+'Balance Sheet'!F11)*Assumptions!G16 -> 87573.867 | H22: =('Balance Sheet'!G5+'Balance Sheet'!G6+'Balance Sheet'!G11)*Assumptions!H16 -> 106971.44 | I22: =('Balance Sheet'!H5+'Balance Sheet'!H6+'Balance Sheet'!H11)*Assumptions!I16 -> 134295.07
A23: Interest expense | B23: -3801 | C23: -3721 | D23: -876 | E23: 0 | F23: 0 | G23: 0 | H23: 0 | I23: 0
A24: Other income (expense), net | B24: -4673 | C24: 17294 | D24: -3258 | E24: 0 | F24: 0 | G24: 0 | H24: 0 | I24: 0
A25: Income (loss) before income taxes | B25: =B20+B22+B23+B24 -> -150575 | C25: =C20+C22+C23+C24 -> 28677 | D25: =D20+D22+D23+D24 -> 69463 | E25: =E20+E22+E23+E24 -> 147204.76 | F25: =F20+F22+F23+F24 -> 258718.85 | G25: =G20+G22+G23+G24 -> 408447.17 | H25: =H20+H22+H23+H24 -> 603285.35 | I25: =I20+I22+I23+I24 -> 854511.49
A26: Income tax expense | B26: 13935 | C26: 24049 | D26: 23552 | E26: =E25*Assumptions!E15 -> 44161.428 | F26: =F25*Assumptions!F15 -> 72441.278 | G26: =G25*Assumptions!G15 -> 110280.74 | H26: =H25*Assumptions!H15 -> 156854.19 | I26: =I25*Assumptions!I15 -> 213627.87
A27: Net income (loss) | B27: =B25-B26 -> -164510 | C27: =C25-C26 -> 4628 | D27: =D25-D26 -> 45911 | E27: =E25-E26 -> 103043.33 | F27: =F25-F26 -> 186277.57 | G27: =G25-G26 -> 298166.43 | H27: =H25-H26 -> 446431.16 | I27: =I25-I26 -> 640883.62
A29: Weighted-average diluted shares outstanding | B29: 49877 | C29: 51819 | D29: 53194 | E29: =D29*(1+Assumptions!E17) -> 53725.94 | F29: =E29*(1+Assumptions!F17) -> 54263.199 | G29: =F29*(1+Assumptions!G17) -> 54805.831 | H29: =G29*(1+Assumptions!H17) -> 55353.89 | I29: =H29*(1+Assumptions!I17) -> 55907.429
A30: Diluted EPS ($) | B30: =B27/B29 -> -3.2983139 | C30: =C27/C29 -> 0.089310871 | D30: =D27/D29 -> 0.86308606 | E30: =E27/E29 -> 1.9179438 | F30: =F27/F29 -> 3.4328527 | G30: =G27/G29 -> 5.4404144 | H30: =H27/H29 -> 8.0650368 | I30: =I27/I29 -> 11.4633
A32: Memo: stock-based compensation expense | B32: 432271 | C32: 504770 | D32: 528153 | E32: =E7*Assumptions!E12 -> 593451.21 | F32: =F7*Assumptions!F12 -> 665534.66 | G32: =G7*Assumptions!G12 -> 747132.45 | H32: =H7*Assumptions!H12 -> 846353.03 | I32: =I7*Assumptions!I12 -> 954746.22
A33: Memo: depreciation (PP&E) | E33: =E7*Assumptions!E13 -> 29672.561 | F33: =F7*Assumptions!F13 -> 35028.14 | G33: =G7*Assumptions!G13 -> 41221.101 | H33: =H7*Assumptions!H13 -> 48363.031 | I33: =I7*Assumptions!I13 -> 56577.554 | K33: Historical split of D&A not disclosed at this level; total D&A per cash flow statement
A34: Memo: amortization of capitalized software | E34: =E7*Assumptions!E14 -> 85308.612 | F34: =F7*Assumptions!F14 -> 100705.9 | G34: =G7*Assumptions!G14 -> 118510.67 | H34: =H7*Assumptions!H14 -> 139043.71 | I34: =I7*Assumptions!I14 -> 162660.47

Sheet Balance Sheet
A1: HubSpot, Inc.; Balance Sheet
A2: (USD in thousands, except per-share amounts) · FY2023A–FY2025A per SEC filings · FY2026E–FY2030E forecast
B3: FY2023A | C3: FY2024A | D3: FY2025A | E3: FY2026E | F3: FY2027E | G3: FY2028E | H3: FY2029E | I3: FY2030E
A4: Assets
A5: Cash and cash equivalents | B5: 387987 | C5: 512667 | D5: 882242 | E5: ='Cash Flow'!E38 -> 1135437 | F5: ='Cash Flow'!F38 -> 1543896.5 | G5: ='Cash Flow'!G38 -> 2098113 | H5: ='Cash Flow'!H38 -> 2878788.1 | I5: ='Cash Flow'!I38 -> 3921319.2
A6: Short-term investments | B6: 1000245 | C6: 1556828 | D6: 821552 | E6: =D6 -> 821552 | F6: =E6 -> 821552 | G6: =F6 -> 821552 | H6: =G6 -> 821552 | I6: =H6 -> 821552 | K6: Short- and long-term investments held flat in forecast; excess cash accumulates in cash & equivalents
A7: Accounts receivable, net | B7: 295303 | C7: 334829 | D7: 419146 | E7: ='Income Statement'!E7*Assumptions!E20/365 -> 497929.96 | F7: ='Income Statement'!F7*Assumptions!F20/365 -> 587800.98 | G7: ='Income Statement'!G7*Assumptions!G20/365 -> 677607.14 | H7: ='Income Statement'!H7*Assumptions!H20/365 -> 795008.72 | I7: ='Income Statement'!I7*Assumptions!I20/365 -> 910666.11
A8: Deferred commission expense | B8: 99326 | C8: 148693 | D8: 226184 | E8: ='Income Statement'!E7*Assumptions!E21 -> 267053.05 | F8: ='Income Statement'!F7*Assumptions!F21 -> 315253.26 | G8: ='Income Statement'!G7*Assumptions!G21 -> 370989.91 | H8: ='Income Statement'!H7*Assumptions!H21 -> 435267.27 | I8: ='Income Statement'!I7*Assumptions!I21 -> 509197.99
A9: Prepaid expenses and other current assets | B9: 88679 | C9: 80586 | D9: 100611 | E9: ='Income Statement'!E7*Assumptions!E23 -> 118690.24 | F9: ='Income Statement'!F7*Assumptions!F23 -> 140112.56 | G9: ='Income Statement'!G7*Assumptions!G23 -> 164884.4 | H9: ='Income Statement'!H7*Assumptions!H23 -> 193452.12 | I9: ='Income Statement'!I7*Assumptions!I23 -> 226310.22
A10: Total current assets | B10: =SUM(B5:B9) -> 1871540 | C10: =SUM(C5:C9) -> 2633603 | D10: =SUM(D5:D9) -> 2449735 | E10: =SUM(E5:E9) -> 2840662.2 | F10: =SUM(F5:F9) -> 3408615.3 | G10: =SUM(G5:G9) -> 4133146.4 | H10: =SUM(H5:H9) -> 5124068.3 | I10: =SUM(I5:I9) -> 6389045.6
A11: Long-term investments | B11: 325703 | C11: 154212 | D11: 136662 | E11: =D11 -> 136662 | F11: =E11 -> 136662 | G11: =F11 -> 136662 | H11: =G11 -> 136662 | I11: =H11 -> 136662
A12: Property and equipment, net | B12: 103331 | C12: 114165 | D12: 141869 | E12: =D12-'Cash Flow'!E19-'Income Statement'!E33 -> 175250.63 | F12: =E12-'Cash Flow'!F19-'Income Statement'!F33 -> 214657.29 | G12: =F12-'Cash Flow'!G19-'Income Statement'!G33 -> 261031.03 | H12: =G12-'Cash Flow'!H19-'Income Statement'!H33 -> 315439.44 | I12: =H12-'Cash Flow'!I19-'Income Statement'!I33 -> 379089.18
A13: Capitalized software development costs, net | B13: 106229 | C13: 154484 | D13: 213794 | E13: =D13-'Cash Flow'!E20-'Income Statement'!E34 -> 284266.33 | F13: =E13-'Cash Flow'!F20-'Income Statement'!F34 -> 367458.16 | G13: =F13-'Cash Flow'!G20-'Income Statement'!G34 -> 465358.28 | H13: =G13-'Cash Flow'!H20-'Income Statement'!H34 -> 580220.48 | I13: =H13-'Cash Flow'!I20-'Income Statement'!I34 -> 714592.17
A14: Operating lease right-of-use assets | B14: 251071 | C14: 216230 | D14: 200821 | E14: =D14 -> 200821 | F14: =E14 -> 200821 | G14: =F14 -> 200821 | H14: =G14 -> 200821 | I14: =H14 -> 200821
A15: Deferred commission expense, noncurrent | B15: 122194 | C15: 160814 | D15: 218991 | E15: ='Income Statement'!E7*Assumptions!E22 -> 259634.91 | F15: ='Income Statement'!F7*Assumptions!F22 -> 306496.23 | G15: ='Income Statement'!G7*Assumptions!G22 -> 360684.63 | H15: ='Income Statement'!H7*Assumptions!H22 -> 423176.52 | I15: ='Income Statement'!I7*Assumptions!I22 -> 495053.6
A16: Other assets | B16: 75247 | C16: 115254 | D16: 165602 | E16: ='Income Statement'!E7*Assumptions!E24 -> 196580.71 | F16: ='Income Statement'!F7*Assumptions!F24 -> 232061.43 | G16: ='Income Statement'!G7*Assumptions!G24 -> 273089.79 | H16: ='Income Statement'!H7*Assumptions!H24 -> 320405.08 | I16: ='Income Statement'!I7*Assumptions!I24 -> 374826.29
A17: Intangible assets, net | B17: 42316 | C17: 37563 | D17: 35225 | E17: =D17 -> 35225 | F17: =E17 -> 35225 | G17: =F17 -> 35225 | H17: =G17 -> 35225 | I17: =H17 -> 35225
A18: Goodwill | B18: 173761 | C18: 209508 | D18: 291452 | E18: =D18 -> 291452 | F18: =E18 -> 291452 | G18: =F18 -> 291452 | H18: =G18 -> 291452 | I18: =H18 -> 291452
A19: Total assets | B19: =B10+SUM(B11:B18) -> 3071392 | C19: =C10+SUM(C11:C18) -> 3795833 | D19: =D10+SUM(D11:D18) -> 3854151 | E19: =E10+SUM(E11:E18) -> 4420554.8 | F19: =F10+SUM(F11:F18) -> 5193448.4 | G19: =G10+SUM(G11:G18) -> 6157470.2 | H19: =H10+SUM(H11:H18) -> 7427469.8 | I19: =I10+SUM(I11:I18) -> 9016766.8
A21: Liabilities
A22: Accounts payable | B22: 9106 | C22: 3649 | D22: 24764 | E22: ='Income Statement'!E7*Assumptions!E25 -> 22254.42 | F22: ='Income Statement'!F7*Assumptions!F25 -> 26271.105 | G22: ='Income Statement'!G7*Assumptions!G25 -> 30915.826 | H22: ='Income Statement'!H7*Assumptions!H25 -> 36272.273 | I22: ='Income Statement'!I7*Assumptions!I25 -> 42433.165
A23: Accrued compensation costs | B23: 53462 | C23: 67442 | D23: 99195 | E23: ='Income Statement'!E7*Assumptions!E26 -> 118690.24 | F23: ='Income Statement'!F7*Assumptions!F26 -> 140112.56 | G23: ='Income Statement'!G7*Assumptions!G26 -> 164884.4 | H23: ='Income Statement'!H7*Assumptions!H26 -> 193452.12 | I23: ='Income Statement'!I7*Assumptions!I26 -> 226310.22
A24: Accrued commissions | B24: 78169 | C24: 102043 | D24: 132003 | E24: ='Income Statement'!E7*Assumptions!E27 -> 155780.94 | F24: ='Income Statement'!F7*Assumptions!F27 -> 183897.74 | G24: ='Income Statement'!G7*Assumptions!G27 -> 216410.78 | H24: ='Income Statement'!H7*Assumptions!H27 -> 253905.91 | I24: ='Income Statement'!I7*Assumptions!I27 -> 297032.16
A25: Accrued expenses and other current liabilities | B25: 94074 | C25: 125135 | D25: 166861 | E25: ='Income Statement'!E7*Assumptions!E28 -> 192871.64 | F25: ='Income Statement'!F7*Assumptions!F28 -> 227682.91 | G25: ='Income Statement'!G7*Assumptions!G28 -> 267937.16 | H25: ='Income Statement'!H7*Assumptions!H28 -> 314359.7 | I25: ='Income Statement'!I7*Assumptions!I28 -> 367754.1
A26: Operating lease liabilities | B26: 35047 | C26: 32693 | D26: 39703 | E26: =D26 -> 39703 | F26: =E26 -> 39703 | G26: =F26 -> 39703 | H26: =G26 -> 39703 | I26: =H26 -> 39703
A27: Convertible senior notes, current | B27: 0 | C27: 458184 | D27: 0 | E27: 0 | F27: 0 | G27: 0 | H27: 0 | I27: 0
A28: Deferred revenue | B28: 672150 | C28: 784253 | D28: 1004945 | E28: ='Income Statement'!E7*Assumptions!E29 -> 1205447.8 | F28: ='Income Statement'!F7*Assumptions!F29 -> 1436153.7 | G28: ='Income Statement'!G7*Assumptions!G29 -> 1700370.4 | H28: ='Income Statement'!H7*Assumptions!H29 -> 2007065.8 | I28: ='Income Statement'!I7*Assumptions!I29 -> 2362112.9
A29: Total current liabilities | B29: =SUM(B22:B28) -> 942008 | C29: =SUM(C22:C28) -> 1573399 | D29: =SUM(D22:D28) -> 1467471 | E29: =SUM(E22:E28) -> 1734748 | F29: =SUM(F22:F28) -> 2053821.1 | G29: =SUM(G22:G28) -> 2420221.6 | H29: =SUM(H22:H28) -> 2844758.8 | I29: =SUM(I22:I28) -> 3335345.5
A30: Operating lease liabilities, noncurrent | B30: 296561 | C30: 254539 | D30: 222602 | E30: =D30 -> 222602 | F30: =E30 -> 222602 | G30: =F30 -> 222602 | H30: =G30 -> 222602 | I30: =H30 -> 222602
A31: Deferred revenue, noncurrent | B31: 5810 | C31: 3969 | D31: 8495 | E31: ='Income Statement'!E7*Assumptions!E30 -> 11127.21 | F31: ='Income Statement'!F7*Assumptions!F30 -> 13135.553 | G31: ='Income Statement'!G7*Assumptions!G30 -> 15457.913 | H31: ='Income Statement'!H7*Assumptions!H30 -> 18136.136 | I31: ='Income Statement'!I7*Assumptions!I30 -> 21216.583
A32: Other long-term liabilities | B32: 36459 | C32: 55640 | D32: 89339 | E32: =D32 -> 89339 | F32: =E32 -> 89339 | G32: =F32 -> 89339 | H32: =G32 -> 89339 | I32: =H32 -> 89339
A33: Convertible senior notes, noncurrent | B33: 456206 | C33: 0 | D33: 0 | E33: 0 | F33: 0 | G33: 0 | H33: 0 | I33: 0
A34: Total liabilities | B34: =B29+SUM(B30:B33) -> 1737044 | C34: =C29+SUM(C30:C33) -> 1887547 | D34: =D29+SUM(D30:D33) -> 1787907 | E34: =E29+SUM(E30:E33) -> 2057816.2 | F34: =F29+SUM(F30:F33) -> 2378897.6 | G34: =G29+SUM(G30:G33) -> 2747620.5 | H34: =H29+SUM(H30:H33) -> 3174835.9 | I34: =I29+SUM(I30:I33) -> 3668503.1
A36: Stockholders' equity
A37: Common stock | B37: 50 | C37: 52 | D37: 53 | E37: =D37 -> 53 | F37: =E37 -> 53 | G37: =F37 -> 53 | H37: =G37 -> 53 | I37: =H37 -> 53
A38: Treasury stock | B38: 0 | C38: 0 | D38: 2 | E38: =D38 -> 2 | F38: =E38 -> 2 | G38: =F38 -> 2 | H38: =G38 -> 2 | I38: =H38 -> 2
A39: Additional paid-in capital | B39: 2136908 | C39: 2713697 | D39: 2814843 | E39: =D39+'Cash Flow'!E7+'Cash Flow'!E27 -> 3483294.2 | F39: =E39+'Cash Flow'!F7+'Cash Flow'!F27 -> 4223828.9 | G39: =F39+'Cash Flow'!G7+'Cash Flow'!G27 -> 5045961.3 | H39: =G39+'Cash Flow'!H7+'Cash Flow'!H27 -> 5967314.4 | I39: =H39+'Cash Flow'!I7+'Cash Flow'!I27 -> 6997060.6
A40: Accumulated other comprehensive income (loss) | B40: 1827 | C40: -5654 | D40: 5244 | E40: =D40 -> 5244 | F40: =E40 -> 5244 | G40: =F40 -> 5244 | H40: =G40 -> 5244 | I40: =H40 -> 5244
A41: Accumulated deficit | B41: -804437 | C41: -799809 | D41: -753898 | E41: =D41+'Income Statement'!E27+'Cash Flow'!E28+'Cash Flow'!E30 -> -1125854.7 | F41: =E41+'Income Statement'!F27+'Cash Flow'!F28+'Cash Flow'!F30 -> -1414577.1 | G41: =F41+'Income Statement'!G27+'Cash Flow'!G28+'Cash Flow'!G30 -> -1641410.7 | H41: =G41+'Income Statement'!H27+'Cash Flow'!H28+'Cash Flow'!H30 -> -1719979.5 | I41: =H41+'Income Statement'!I27+'Cash Flow'!I28+'Cash Flow'!I30 -> -1654095.9
A42: Total stockholders' equity | B42: =SUM(B37:B41) -> 1334348 | C42: =SUM(C37:C41) -> 1908286 | D42: =SUM(D37:D41) -> 2066244 | E42: =SUM(E37:E41) -> 2362738.5 | F42: =SUM(F37:F41) -> 2814550.8 | G42: =SUM(G37:G41) -> 3409849.7 | H42: =SUM(H37:H41) -> 4252633.9 | I42: =SUM(I37:I41) -> 5348263.7
A43: Total liabilities and equity | B43: =B34+B42 -> 3071392 | C43: =C34+C42 -> 3795833 | D43: =D34+D42 -> 3854151 | E43: =E34+E42 -> 4420554.8 | F43: =F34+F42 -> 5193448.4 | G43: =G34+G42 -> 6157470.2 | H43: =H34+H42 -> 7427469.8 | I43: =I34+I42 -> 9016766.8
A45: Balance check (assets − liabilities & equity) | B45: =B19-B43 -> 0 | C45: =C19-C43 -> 0 | D45: =D19-D43 -> 0 | E45: =E19-E43 -> 0 | F45: =F19-F43 -> 0 | G45: =G19-G43 -> 0 | H45: =H19-H43 -> 0 | I45: =I19-I43 -> 0 | K45: Must be zero in every period

Sheet Cash Flow
A1: HubSpot, Inc.; Statement of Cash Flows
A2: (USD in thousands, except per-share amounts) · FY2023A–FY2025A per SEC filings · FY2026E–FY2030E forecast
B3: FY2023A | C3: FY2024A | D3: FY2025A | E3: FY2026E | F3: FY2027E | G3: FY2028E | H3: FY2029E | I3: FY2030E
A4: Operating activities
A5: Net income (loss) | B5: -164510 | C5: 4628 | D5: 45911 | E5: ='Income Statement'!E27 -> 103043.33 | F5: ='Income Statement'!F27 -> 186277.57 | G5: ='Income Statement'!G27 -> 298166.43 | H5: ='Income Statement'!H27 -> 446431.16 | I5: ='Income Statement'!I27 -> 640883.62
A6: Depreciation and amortization | B6: 72673 | C6: 96828 | D6: 136295 | E6: ='Income Statement'!E33+'Income Statement'!E34 -> 114981.17 | F6: ='Income Statement'!F33+'Income Statement'!F34 -> 135734.04 | G6: ='Income Statement'!G33+'Income Statement'!G34 -> 159731.77 | H6: ='Income Statement'!H33+'Income Statement'!H34 -> 187406.74 | I6: ='Income Statement'!I33+'Income Statement'!I34 -> 219238.02
A7: Stock-based compensation | B7: 432271 | C7: 504770 | D7: 528153 | E7: ='Income Statement'!E32 -> 593451.21 | F7: ='Income Statement'!F32 -> 665534.66 | G7: ='Income Statement'!G32 -> 747132.45 | H7: ='Income Statement'!H32 -> 846353.03 | I7: ='Income Statement'!I32 -> 954746.22
A8: Other non-cash adjustments, net | B8: 28255 | C8: -64463 | D8: -45162 | E8: 0 | F8: 0 | G8: 0 | H8: 0 | I8: 0 | K8: Historical: bond discount accretion, strategic investment marks, deferred taxes and other, per filings
A9: (Increase) in accounts receivable | B9: -57618 | C9: -48428 | D9: -64003 | E9: =-('Balance Sheet'!E7-'Balance Sheet'!D7) -> -78783.955 | F9: =-('Balance Sheet'!F7-'Balance Sheet'!E7) -> -89871.028 | G9: =-('Balance Sheet'!G7-'Balance Sheet'!F7) -> -89806.155 | H9: =-('Balance Sheet'!H7-'Balance Sheet'!G7) -> -117401.58 | I9: =-('Balance Sheet'!I7-'Balance Sheet'!H7) -> -115657.39
A10: (Increase) in deferred commission expense | B10: -81178 | C10: -96687 | D10: -117032 | E10: =-('Balance Sheet'!E8-'Balance Sheet'!D8)-('Balance Sheet'!E15-'Balance Sheet'!D15) -> -81512.95 | F10: =-('Balance Sheet'!F8-'Balance Sheet'!E8)-('Balance Sheet'!F15-'Balance Sheet'!E15) -> -95061.538 | G10: =-('Balance Sheet'!G8-'Balance Sheet'!F8)-('Balance Sheet'!G15-'Balance Sheet'!F15) -> -109925.05 | H10: =-('Balance Sheet'!H8-'Balance Sheet'!G8)-('Balance Sheet'!H15-'Balance Sheet'!G15) -> -126769.25 | I10: =-('Balance Sheet'!I8-'Balance Sheet'!H8)-('Balance Sheet'!I15-'Balance Sheet'!H15) -> -145807.79
A11: (Increase) in prepaid and other assets | B11: -47048 | C11: -4415 | D11: -34060 | E11: =-('Balance Sheet'!E9-'Balance Sheet'!D9)-('Balance Sheet'!E16-'Balance Sheet'!D16) -> -49057.956 | F11: =-('Balance Sheet'!F9-'Balance Sheet'!E9)-('Balance Sheet'!F16-'Balance Sheet'!E16) -> -56903.033 | G11: =-('Balance Sheet'!G9-'Balance Sheet'!F9)-('Balance Sheet'!G16-'Balance Sheet'!F16) -> -65800.207 | H11: =-('Balance Sheet'!H9-'Balance Sheet'!G9)-('Balance Sheet'!H16-'Balance Sheet'!G16) -> -75883.002 | I11: =-('Balance Sheet'!I9-'Balance Sheet'!H9)-('Balance Sheet'!I16-'Balance Sheet'!H16) -> -87279.311
A12: Increase (decrease) in accounts payable | B12: -14031 | C12: -4577 | D12: 18999 | E12: ='Balance Sheet'!E22-'Balance Sheet'!D22 -> -2509.5796 | F12: ='Balance Sheet'!F22-'Balance Sheet'!E22 -> 4016.6847 | G12: ='Balance Sheet'!G22-'Balance Sheet'!F22 -> 4644.7205 | H12: ='Balance Sheet'!H22-'Balance Sheet'!G22 -> 5356.4472 | I12: ='Balance Sheet'!I22-'Balance Sheet'!H22 -> 6160.8925
A13: Increase in accrued expenses and other liabilities | B13: 79947 | C13: 89129 | D13: 117971 | E13: =('Balance Sheet'!E23-'Balance Sheet'!D23)+('Balance Sheet'!E24-'Balance Sheet'!D24)+('Balance Sheet'!E25-'Balance Sheet'!D25) -> 69283.829 | F13: =('Balance Sheet'!F23-'Balance Sheet'!E23)+('Balance Sheet'!F24-'Balance Sheet'!E24)+('Balance Sheet'!F25-'Balance Sheet'!E25) -> 84350.379 | G13: =('Balance Sheet'!G23-'Balance Sheet'!F23)+('Balance Sheet'!G24-'Balance Sheet'!F24)+('Balance Sheet'!G25-'Balance Sheet'!F25) -> 97539.131 | H13: =('Balance Sheet'!H23-'Balance Sheet'!G23)+('Balance Sheet'!H24-'Balance Sheet'!G24)+('Balance Sheet'!H25-'Balance Sheet'!G25) -> 112485.39 | I13: =('Balance Sheet'!I23-'Balance Sheet'!H23)+('Balance Sheet'!I24-'Balance Sheet'!H24)+('Balance Sheet'!I25-'Balance Sheet'!H25) -> 129378.74
A14: Increase in deferred revenue | B14: 109926 | C14: 131038 | D14: 183875 | E14: =('Balance Sheet'!E28-'Balance Sheet'!D28)+('Balance Sheet'!E31-'Balance Sheet'!D31) -> 203134.98 | F14: =('Balance Sheet'!F28-'Balance Sheet'!E28)+('Balance Sheet'!F31-'Balance Sheet'!E31) -> 232714.32 | G14: =('Balance Sheet'!G28-'Balance Sheet'!F28)+('Balance Sheet'!G31-'Balance Sheet'!F31) -> 266539.02 | H14: =('Balance Sheet'!H28-'Balance Sheet'!G28)+('Balance Sheet'!H31-'Balance Sheet'!G31) -> 309373.58 | I14: =('Balance Sheet'!I28-'Balance Sheet'!H28)+('Balance Sheet'!I31-'Balance Sheet'!H31) -> 358127.55
A15: Change in operating leases, net | B15: -7716 | C15: -9224 | D15: -10230 | E15: 0 | F15: 0 | G15: 0 | H15: 0 | I15: 0
A16: Net cash provided by operating activities | B16: =SUM(B5:B15) -> 350971 | C16: =SUM(C5:C15) -> 598599 | D16: =SUM(D5:D15) -> 760717 | E16: =SUM(E5:E15) -> 872030.09 | F16: =SUM(F5:F15) -> 1066792.1 | G16: =SUM(G5:G15) -> 1308222.1 | H16: =SUM(H5:H15) -> 1587352.5 | I16: =SUM(I5:I15) -> 1959790.6
A18: Investing activities
A19: Purchases of property and equipment | B19: -33718 | C19: -37939 | D19: -53165 | E19: =-'Income Statement'!E7*Assumptions!E31 -> -63054.191 | F19: =-'Income Statement'!F7*Assumptions!F31 -> -74434.798 | G19: =-'Income Statement'!G7*Assumptions!G31 -> -87594.839 | H19: =-'Income Statement'!H7*Assumptions!H31 -> -102771.44 | I19: =-'Income Statement'!I7*Assumptions!I31 -> -120227.3
A20: Capitalization of software development costs | B20: -66372 | C20: -89636 | D20: -130624 | E20: =-'Income Statement'!E7*Assumptions!E32 -> -155780.94 | F20: =-'Income Statement'!F7*Assumptions!F32 -> -183897.74 | G20: =-'Income Statement'!G7*Assumptions!G32 -> -216410.78 | H20: =-'Income Statement'!H7*Assumptions!H32 -> -253905.91 | I20: =-'Income Statement'!I7*Assumptions!I32 -> -297032.16
A21: Net (purchases) maturities of investments | B21: -77970 | C21: -333012 | D21: 793389 | E21: 0 | F21: 0 | G21: 0 | H21: 0 | I21: 0 | K21: Forecast: investment portfolio held flat; excess cash retained in cash & equivalents
A22: Business acquisitions, net of cash acquired | B22: -142129 | C22: -40438 | D22: -87608 | E22: 0 | F22: 0 | G22: 0 | H22: 0 | I22: 0
A23: Other investing activities | B23: -14577 | C23: -14836 | D23: -30219 | E23: 0 | F23: 0 | G23: 0 | H23: 0 | I23: 0
A24: Net cash provided by (used in) investing activities | B24: =SUM(B19:B23) -> -334766 | C24: =SUM(C19:C23) -> -515861 | D24: =SUM(D19:D23) -> 491773 | E24: =SUM(E19:E23) -> -218835.13 | F24: =SUM(F19:F23) -> -258332.53 | G24: =SUM(G19:G23) -> -304005.62 | H24: =SUM(H19:H23) -> -356677.35 | I24: =SUM(I19:I23) -> -417259.46
A26: Financing activities
A27: Proceeds from issuance of stock under stock plans | B27: 47738 | C27: 75501 | D27: 71394 | E27: =Assumptions!E36 -> 75000 | F27: =Assumptions!F36 -> 75000 | G27: =Assumptions!G36 -> 75000 | H27: =Assumptions!H36 -> 75000 | I27: =Assumptions!I36 -> 75000
A28: Repurchases of common stock | B28: 0 | C28: 0 | D28: -500019 | E28: =-Assumptions!E35 -> -450000 | F28: =-Assumptions!F35 -> -450000 | G28: =-Assumptions!G35 -> -500000 | H28: =-Assumptions!H35 -> -500000 | I28: =-Assumptions!I35 -> -550000
A29: Repayment of convertible notes | B29: -13 | C29: -57 | D29: -459811 | E29: 0 | F29: 0 | G29: 0 | H29: 0 | I29: 0
A30: Employee taxes paid on net share settlement | B30: -10714 | C30: -21949 | D30: -21573 | E30: =-Assumptions!E37 -> -25000 | F30: =-Assumptions!F37 -> -25000 | G30: =-Assumptions!G37 -> -25000 | H30: =-Assumptions!H37 -> -25000 | I30: =-Assumptions!I37 -> -25000
A31: Net cash provided by (used in) financing activities | B31: =SUM(B27:B30) -> 37011 | C31: =SUM(C27:C30) -> 53495 | D31: =SUM(D27:D30) -> -910009 | E31: =SUM(E27:E30) -> -400000 | F31: =SUM(F27:F30) -> -400000 | G31: =SUM(G27:G30) -> -450000 | H31: =SUM(H27:H30) -> -450000 | I31: =SUM(I27:I30) -> -500000
A33: Effect of exchange rate changes on cash | B33: 4649 | C33: -11553 | D33: 25744 | E33: 0 | F33: 0 | G33: 0 | H33: 0 | I33: 0
A34: Net increase in cash | B34: =B16+B24+B31+B33 -> 57865 | C34: =C16+C24+C31+C33 -> 124680 | D34: =D16+D24+D31+D33 -> 368225 | E34: =E16+E24+E31+E33 -> 253194.95 | F34: =F16+F24+F31+F33 -> 408459.53 | G34: =G16+G24+G31+G33 -> 554216.49 | H34: =H16+H24+H31+H33 -> 780675.16 | I34: =I16+I24+I31+I33 -> 1042531.1
A35: Cash, equivalents and restricted cash, beginning | B35: 334175 | C35: 392040 | D35: 516720 | E35: =D38 -> 882242 | F35: =E38 -> 1135437 | G35: =F38 -> 1543896.5 | H35: =G38 -> 2098113 | I35: =H38 -> 2878788.1
A36: Cash, equivalents and restricted cash, ending | B36: =B35+B34 -> 392040 | C36: =C35+C34 -> 516720 | D36: =D35+D34 -> 884945 | E36: =E35+E34 -> 1135437 | F36: =F35+F34 -> 1543896.5 | G36: =G35+G34 -> 2098113 | H36: =H35+H34 -> 2878788.1 | I36: =I35+I34 -> 3921319.2
A37: Less: restricted cash | B37: 4053 | C37: 4053 | D37: 2703 | E37: 0 | F37: 0 | G37: 0 | H37: 0 | I37: 0
A38: Cash and cash equivalents per balance sheet | B38: =B36-B37 -> 387987 | C38: =C36-C37 -> 512667 | D38: =D36-D37 -> 882242 | E38: =E36-E37 -> 1135437 | F38: =F36-F37 -> 1543896.5 | G38: =G36-G37 -> 2098113 | H38: =H36-H37 -> 2878788.1 | I38: =I36-I37 -> 3921319.2 | K38: Links to cash on the balance sheet

Sheet Budget vs Actual
A1: HubSpot, Inc.; Budget vs Actual Variance
A2: FY2025 actual vs FY2025 budget (USD in thousands, except per-share) · Budget seeded from company guidance where published; all budget cells editable
A4: Variance flag threshold (|variance %| above this is flagged) | B4: 0.1
A6: Metric | B6: FY2025 Budget | C6: Budget source | D6: Override budget | E6: Effective budget | F6: FY2025 Actual | G6: Variance $ | H6: Variance % | I6: Flag
A7: Total revenue | B7: 2990000 | C7: Company FY25 guidance (Feb 12, 2025): $2,985–2,995M | E7: =IF(D7="",B7,D7) -> 2990000 | F7: ='Income Statement'!D7 -> 3131266 | G7: =F7-E7 -> 141266 | H7: =IF(E7=0,"",G7/E7) -> 0.047246154 | I7: =IF(H7="","",IF(ABS(H7)>$B$4,"⚠ REVIEW","OK")) -> OK
A8: Gross profit | B8: 2600000 | C8: Placeholder · replace with your budget | E8: =IF(D8="",B8,D8) -> 2600000 | F8: ='Income Statement'!D12 -> 2622779 | G8: =F8-E8 -> 22779 | H8: =IF(E8=0,"",G8/E8) -> 0.0087611538 | I8: =IF(H8="","",IF(ABS(H8)>$B$4,"⚠ REVIEW","OK")) -> OK
A9: Total operating expenses | B9: 2570000 | C9: Placeholder · replace with your budget | E9: =IF(D9="",B9,D9) -> 2570000 | F9: ='Income Statement'!D19 -> 2615400 | G9: =F9-E9 -> 45400 | H9: =IF(E9=0,"",G9/E9) -> 0.01766537 | I9: =IF(H9="","",IF(ABS(H9)>$B$4,"⚠ REVIEW","OK")) -> OK
A10: Income (loss) from operations (GAAP) | B10: 30000 | C10: Placeholder · replace with your budget | E10: =IF(D10="",B10,D10) -> 30000 | F10: ='Income Statement'!D20 -> 7379 | G10: =F10-E10 -> -22621 | H10: =IF(E10=0,"",G10/E10) -> -0.75403333 | I10: =IF(H10="","",IF(ABS(H10)>$B$4,"⚠ REVIEW","OK")) -> ⚠ REVIEW
A11: Net income (GAAP) | B11: 60000 | C11: Placeholder · replace with your budget | E11: =IF(D11="",B11,D11) -> 60000 | F11: ='Income Statement'!D27 -> 45911 | G11: =F11-E11 -> -14089 | H11: =IF(E11=0,"",G11/E11) -> -0.23481667 | I11: =IF(H11="","",IF(ABS(H11)>$B$4,"⚠ REVIEW","OK")) -> ⚠ REVIEW
A12: Non-GAAP operating income | B12: 545000 | C12: Company FY25 guidance: $543–547M (~18% margin) | E12: =IF(D12="",B12,D12) -> 545000 | F12: 581901 | G12: =F12-E12 -> 36901 | H12: =IF(E12=0,"",G12/E12) -> 0.067708257 | I12: =IF(H12="","",IF(ABS(H12)>$B$4,"⚠ REVIEW","OK")) -> OK
A13: Non-GAAP diluted EPS ($) | B13: 9.15 | C13: Company FY25 guidance: $9.11–9.19 | E13: =IF(D13="",B13,D13) -> 9.15 | F13: 9.7 | G13: =F13-E13 -> 0.55 | H13: =IF(E13=0,"",G13/E13) -> 0.06010929 | I13: =IF(H13="","",IF(ABS(H13)>$B$4,"⚠ REVIEW","OK")) -> OK
A14: Net cash provided by operating activities | B14: 700000 | C14: Placeholder · replace with your budget | E14: =IF(D14="",B14,D14) -> 700000 | F14: ='Cash Flow'!D16 -> 760717 | G14: =F14-E14 -> 60717 | H14: =IF(E14=0,"",G14/E14) -> 0.086738571 | I14: =IF(H14="","",IF(ABS(H14)>$B$4,"⚠ REVIEW","OK")) -> OK
A15: Free cash flow (non-GAAP) | B15: 550000 | C15: Placeholder · replace with your budget | E15: =IF(D15="",B15,D15) -> 550000 | F15: 594916 | G15: =F15-E15 -> 44916 | H15: =IF(E15=0,"",G15/E15) -> 0.081665455 | I15: =IF(H15="","",IF(ABS(H15)>$B$4,"⚠ REVIEW","OK")) -> OK
A17: Notes:
A18: • Budget column is seeded with the midpoint of company guidance issued at the start of FY2025 where published (see Budget source).
A19: • Rows marked "Placeholder" carry illustrative budgets; overwrite them, or type your own number in the yellow Override column (it takes precedence).
A20: • GAAP actuals pull live from the statement tabs (green); non-GAAP actuals are per the company's Q4 FY2025 earnings release.
A21: • Rows turn red automatically when |Variance %| exceeds the threshold in B4.

Sheet Market Inputs
A1: HubSpot, Inc.; Market Inputs
A2: Snapshot as of market close July 17, 2026 · All values are inputs (blue); see REFRESH section to wire live updates
A4: Data as of: | B4: July 17, 2026 | C4: Last refreshed: | D4: 2026-07-20 (initial snapshot)
A6: INTEREST RATES
A7: Fed funds target (upper bound) | B7: 0.0375 | F7: Range 3.50%–3.75%; unchanged at June 17, 2026 FOMC
A8: SOFR | B8: 0.0364 | F8: NY Fed, latest print
A9: 3-month T-bill (CMT) | B9: 0.0384 | F9: Fed H.15, Jul 16, 2026
A10: 2-year Treasury | B10: 0.0418 | F10: Close Jul 17, 2026
A11: 10-year Treasury | B11: 0.0455 | F11: Close Jul 17, 2026
A12: 30-year Treasury | B12: 0.0506 | F12: Close Jul 17, 2026
A14: EQUITY MARKET DATA: PEER SET
B15: PLTR | C15: HUBS | D15: SOFI
A16: Share price ($) | B16: 132.38 | C16: 224.26 | D16: 17.28
A17: Market cap ($mm) | B17: 317400 | C17: 11490 | D17: 22170
A18: Enterprise value ($mm) | B18: 309500 | C18: 10040 | D18: 20520
A19: Trailing P/E (x) | B19: 148.8 | C19: 119.2 | D19: 38.8
A20: Forward P/E (x) | B20: 83.3 | C20: 16.4 | D20: 26.4
A21: EV / Revenue, TTM (x) | B21: 59.3 | C21: 3 | D21: 5.2
A22: TTM revenue ($mm) | B22: 5220 | C22: 3300 | D22: 3910
A24: IMPLIED VALUATION CROSS-CHECK (uses this model's forecast)
A25: Selected EV / Revenue multiple (x) | B25: =C21 -> 3 | F25: Defaults to this company's current multiple; flex it or use a peer's
A26: Model FY2026E revenue ($000s) | B26: ='Income Statement'!E7 -> 3709070.1
A27: Implied enterprise value ($mm) | B27: =B25*B26/1000 -> 11127.21
A28: Current enterprise value ($mm) | B28: =C18 -> 10040
A29: Implied premium / (discount) to current EV | B29: =B27/B28-1 -> 0.10828787
A31: Selected forward P/E multiple (x) | B31: =C20 -> 16.4 | F31: Note: HUBS consensus forward P/E is non-GAAP-based; pair the model's GAAP net income with a GAAP multiple (or swap in non-GAAP EPS) for an apples-to-apples read
A32: Model FY2026E net income ($000s) | B32: ='Income Statement'!E27 -> 103043.33
A33: Implied market capitalization ($mm) | B33: =B31*B32/1000 -> 1689.9107
A34: Current market capitalization ($mm) | B34: =C17 -> 11490
A35: Implied premium / (discount) to current market cap | B35: =B33/B34-1 -> -0.85292335
A37: REFRESH: MAKE THIS TAB LIVE (one-time setup, ~2 minutes in Excel)
A38: 1. Excel ▸ Data ▸ Get Data (Power Query) ▸ From Other Sources ▸ From Web.
A39: 2. Treasury yields (CSV, no key needed): https://home.treasury.gov/resource-center/data-chart-center/interest-rates/daily-treasury-rates.csv/2026/all?type=daily_treasury_yield_curve&field_tdr_date_value=2026&page&_format=csv
A40: 3. Load the query to a new sheet; point the blue rate cells above at the latest row (e.g. =INDEX(...)).
A41: 4. Share prices (JSON): https://query1.finance.yahoo.com/v8/finance/chart/HUBS ; Power Query ▸ From Web, drill to chart.result.meta.regularMarketPrice.
A42: 5. After setup, Data ▸ Refresh All re-pulls everything with one click.
A43: 6. Until then this tab is a dated snapshot (see B4); or ask Claude to refresh the numbers any time.
A44: Sources for this snapshot: Fed H.15 (Jul 17, 2026), NY Fed SOFR, stockanalysis.com / S&P Global (Jul 17–19, 2026).

Sheet Competitor Benchmarking
A1: HubSpot, Inc.; Competitor Benchmarking
A2: Company column pulls live from this model (FY2025 actuals; FY2026E is scenario-aware) · comps per latest reported fiscal year, valuations as of July 17–20, 2026 · industry benchmarks: Clouded Judgement SaaS medians (7/10/26) and US bank norms
A4: Metric | B4: HubSpot (model) | C4: Salesforce (CRM, FY ended 1/26) | D4: monday.com (MNDY, FY2025) | E4: Peer median | F4: Industry benchmark | H4: What it means
A5: Latest FY revenue ($mm) | B5: ='Income Statement'!D7/1000 -> 3131.266 | C5: 41533 | D5: 1232 | E5: =MEDIAN(B5:D5) -> 3131.266 | F5: — | H5: HubSpot sits between the mega-platform (CRM, 13x its size) and the SMB challenger (MNDY, 40% its size).
A6: Revenue growth · FY2025 % | B6: ='Income Statement'!D7/'Income Statement'!C7-1 -> 0.19170876 | C6: 0.1 | D6: 0.27 | E6: =MEDIAN(B6:D6) -> 0.19170876 | F6: 0.13 | H6: 19% growth beats the 13% SaaS median and CRM (10%), trails MNDY (27%); solidly in the mid-growth bucket.
A7: Revenue growth · FY2026E (model, scenario-aware) % | B7: ='Income Statement'!E7/'Income Statement'!D7-1 -> 0.1845273 | C7: n/a | D7: n/a | F7: — | H7: Model FY26E growth (scenario-aware) of ~18% assumes NRR recovery plus steady customer adds; see Revenue Drivers.
A8: GAAP gross margin · FY2025 % | B8: ='Income Statement'!D12/'Income Statement'!D7 -> 0.83760977 | C8: 0.777 | D8: 0.89 | E8: =MEDIAN(B8:D8) -> 0.83760977 | F8: 0.76 | H8: 84% GAAP gross margin is top-decile; above CRM and the median, just below MNDY's 89%.
A9: GAAP operating margin · FY2025 % | B9: ='Income Statement'!D20/'Income Statement'!D7 -> 0.0023565548 | C9: 0.201 | D9: -0.001 | E9: =MEDIAN(B9:D9) -> 0.0023565548 | F9: 0.02 | H9: GAAP operating margin ~0% vs CRM's 20% reflects heavy SBC; non-GAAP operating margin was 18.6% in FY25.
A10: Free cash flow margin · FY2025 % | B10: =('Cash Flow'!D16+'Cash Flow'!D19+'Cash Flow'!D20)/'Income Statement'!D7 -> 0.18424752 | C10: 0.347 | D10: 0.262 | E10: =MEDIAN(B10:D10) -> 0.262 | F10: 0.21 | H10: 18% FCF margin (after capitalized software) is just below the 21% median; operating leverage is still building.
A11: Rule of 40 (growth + FCF margin) | B11: =B6+B10 -> 0.37595628 | C11: =C6+C10 -> 0.447 | D11: =D6+D10 -> 0.532 | E11: =MEDIAN(B11:D11) -> 0.447 | F11: 0.34 | H11: Rule of 40 at ~38% is just under the bar; either growth re-acceleration or FCF expansion pushes it through.
A12: EV / Revenue (TTM) (x) | B12: ='Market Inputs'!C18/'Market Inputs'!C22 -> 3.0424242 | C12: 4 | D12: 1.8 | E12: =MEDIAN(B12:D12) -> 3.0424242 | F12: 5.4 | H12: At 3.0x TTM revenue HubSpot trades BELOW the 5.4x mid-growth bucket median; the market is pricing it like a low-growth asset despite 19% growth.
A13: Forward P/E (x, non-GAAP consensus basis) | B13: ='Market Inputs'!C20 -> 16.4 | C13: 12.3 | D13: 17.1 | E13: =MEDIAN(B13:D13) -> 16.4 | F13: ~21x S&P 500 | H13: 16x forward earnings (non-GAAP basis) is a modest premium to CRM (12x); cheap relative to its history and growth.
A15: INDUSTRY BENCHMARK NOTES
A16: • SaaS medians per Clouded Judgement (Altimeter, 7/10/26): NTM growth 13% · GAAP gross margin 76% · operating margin 2% · FCF margin 21% · NRR 110% · EV/NTM revenue: overall 3.5x, high-growth (>22%) 20.3x, mid-growth (15–22%) 5.4x, low-growth 2.8x.
A17: • Rule of 40 = revenue growth % + FCF margin % ≥ 40% is the standard bar for a healthy software business.
A19: TAKEAWAYS: WHAT THIS COMPARISON MEANS
A20: • HubSpot's operating metrics (19% growth, 84% gross margin, ~38% Rule of 40) screen mid-pack-or-better, but its 3.0x EV/revenue sits below the mid-growth SaaS bucket median of 5.4x; a potential re-rating gap.
A21: • The GAAP/non-GAAP spread is the story: ~0% GAAP operating margin vs 18.6% non-GAAP is almost entirely stock-based comp (~17% of revenue in the model assumptions).
A22: • Versus Salesforce, HubSpot trades growth for margin; versus monday.com, it trades growth for scale and a stickier multi-hub platform.
A24: Sources: company Q4/FY earnings releases and 10-Ks (SEC EDGAR); stockanalysis.com / S&P Global valuations Jul 17–20, 2026; cloudedjudgement.substack.com 7/10/26; multiples.vc Jul 2026. Comp forward P/Es are consensus (non-GAAP) based.

Sheet Version History
A1: HubSpot, Inc.; Version History
A2: Log of every assumptions refresh: what changed, when, and why. Add a new row each time inputs are updated.
A4: Version | B4: Date | C4: Changed by | D4: What changed | E4: Why
A5: 1.0 | B5: 2026-07-19 | C5: A. Pardhootman | D5: Initial build: FY2023–FY2025 actuals per SEC filings; FY2026–FY2030 top-down forecast; Assumptions, Income Statement, Balance Sheet, Cash Flow and Cover with sheet links. | E5: Portfolio work sample: integrated three-statement model with balance and cash tie-out checks.
A6: 1.1 | B6: 2026-07-20 | C6: A. Pardhootman | D6: Added Budget vs Actual tab (FY2025 vs company guidance, 10% variance flag with conditional formatting) and Market Inputs tab (rates and valuation multiples snapshot as of 7/17/26, implied-valuation cross-check, Power Query refresh guide). | E6: Variance discipline against real guidance; live market context for the forecast.
A7: 1.2 | B7: 2026-07-20 | C7: A. Pardhootman | D7: Rebuilt revenue as a bottoms-up Revenue Drivers tab (customer roll-forward (CAC/churn), NRR expansion, first-year ARPC); superseded top-down assumption rows relabeled as OUTPUT. | E7: Unit-economics realism: forecast driven by operating metrics rather than a single growth rate.
A8: 1.3 | B8: 2026-07-20 | C8: A. Pardhootman | D8: Added Regional Breakdown tab: NA / Europe / APAC mix from 10-K geographic disclosures, customer splits, and a scenario selector with per-region growth deltas feeding the Income Statement. | E8: Geographic visibility and one-cell scenario analysis across the full model.
A9: 1.4 | B9: 2026-07-20 | C9: A. Pardhootman | D9: Added Competitor Benchmarking tab vs Salesforce and monday.com + SaaS industry medians; company column pulls live from the model with interpretation and takeaways. | E9: Relative context: absolute metrics only matter versus peers and industry medians.
A10: 1.5 | B10: 2026-07-20 | C10: A. Pardhootman | D10: Renamed scenarios to Standard Case / Best Case / Low Case across the selector, delta rows and commentary; companion interactive HTML dashboard extracted from this workbook under all three scenarios. | E10: Clearer scenario language for non-technical reviewers; browser-based review experience.
A11: 1.6 | B11: 2026-07-20 | C11: A. Pardhootman | D11: Added this Version History tab. | E11: Change auditability: every future assumptions refresh gets logged here.
A12: 1.7 | B12: 2026-07-20 | C12: A. Pardhootman | D12: Added market-data refresh infrastructure: "Last refreshed" stamp on Market Inputs, market_data.js live feed consumed by the dashboard, a Refresh button in the dashboard, and companion script refresh_market_data.py that updates the feed, this workbook's Market Inputs and this log. | E12: Keep valuation context current and visibly timestamped for reviewers.
A13: 1.8 | B13: 2026-07-20 | C13: A. Pardhootman | D13: Applied workbook protection: all formulas, labels and structure locked with a password on every tab; blue/yellow input cells (assumptions, scenario selector, budget overrides) remain editable so the model stays interactive. | E13: Distribution protection: models are downloadable from the public portfolio site; viewers can flex inputs but cannot alter or break the model.
A14: 1.9 | B14: 2026-07-20 | C14: A. Pardhootman | D14: Copy edit across all tabs: punctuation and separator cleanup for a natural reading style; no numbers or formulas changed. | E14: Readability pass ahead of public distribution.
A16: How to log a refresh: add a row (yellow cells above are ready) with the new version number, date, your name, the cells/tabs you changed (e.g. "Assumptions F7: FY27 revenue growth 45% → 40% after Q1 FY27 print"), and the reason. Keep one row per refresh so the audit trail stays readable.

Sheet Sources
A1: Hubspot, Inc.; Data Sources & Citations
A2: Every input in this model, where it comes from, and how current it is. Click "Open ↗" for the underlying source. Refresh stamps also appear on Market Inputs; refreshes are logged in Version History.
A4: Data input | B4: Used on tab(s) | C4: Source / citation | D4: Link | E4: Last updated | F4: How it refreshes
A5: COMPANY FINANCIALS & DISCLOSURES
A6: FY2025 & FY2024 income statement, balance sheet, cash flow | B6: Income Statement · Balance Sheet · Cash Flow | C6: HubSpot Q4 FY2025 earnings release, 8-K Ex. 99.1, filed Feb 11, 2026 | D6: =HYPERLINK("https://www.sec.gov/Archives/edgar/data/1404655/000119312526046563/hubs-ex99_1.htm","Open ↗") -> Open ↗ | E6: 2026-07-19 | F6: Static actuals · restate on next annual filing
A7: FY2023 financial statements (as revised) | B7: Income Statement · Balance Sheet · Cash Flow | C7: HubSpot Q4 FY2024 earnings release, 8-K Ex. 99.1, filed Feb 12, 2025 | D7: =HYPERLINK("https://www.sec.gov/Archives/edgar/data/1404655/000095017025018839/hubs-ex99_1.htm","Open ↗") -> Open ↗ | E7: 2026-07-19 | F7: Static actuals
A8: Revenue by region (Americas / Europe / Asia Pacific) | B8: Regional Breakdown | C8: FY2025 Form 10-K, geographic data note, filed Feb 11, 2026 | D8: =HYPERLINK("https://www.sec.gov/Archives/edgar/data/1404655/000119312526046646/R76.htm","Open ↗") -> Open ↗ | E8: 2026-07-20 | F8: Static · update on next 10-K
A9: Customer counts (205,091 → 288,706), ARPC, net revenue retention | B9: Revenue Drivers | C9: Q4 FY2023–FY2025 releases; NRR ~101.8% (FY24) / ~103.5% (FY25) per earnings calls | D9: =HYPERLINK("https://ir.hubspot.com/news-releases/news-release-details/hubspot-reports-q4-and-full-year-2023-results","Open ↗") -> Open ↗ | E9: 2026-07-20 | F9: Static · update quarterly; CAC and churn are analyst estimates
A10: GUIDANCE & BUDGET
A11: FY2025 guidance (revenue, non-GAAP op income, non-GAAP EPS) | B11: Budget vs Actual | C11: Issued with Q4 FY2024 release, Feb 12, 2025 ($2,985–2,995M revenue) | D11: =HYPERLINK("https://www.sec.gov/Archives/edgar/data/1404655/000095017025018839/hubs-ex99_1.htm","Open ↗") -> Open ↗ | E11: 2026-07-20 | F11: Static · replace with FY2026 guidance next cycle
A12: MARKET DATA
A13: US Treasury yield curve (3M/2Y/10Y/30Y) | B13: Market Inputs | C13: US Treasury daily yield curve; Fed H.15 release (Jul 17, 2026) | D13: =HYPERLINK("https://home.treasury.gov/resource-center/data-chart-center/interest-rates/","Open ↗") -> Open ↗ | E13: 2026-07-17 | F13: refresh_market_data.py or dashboard ⟳ button
A14: Fed funds target & SOFR | B14: Market Inputs | C14: FOMC statement (Jun 17, 2026); NY Fed SOFR reference rate | D14: =HYPERLINK("https://www.newyorkfed.org/markets/reference-rates/sofr","Open ↗") -> Open ↗ | E14: 2026-07-17 | F14: refresh_market_data.py (manual for Fed funds)
A15: Share price, market cap, EV, P/E, EV/Revenue | B15: Market Inputs · Competitor Benchmarking | C15: stockanalysis.com (HUBS); data: S&P Global Market Intelligence, close Jul 17, 2026 | D15: =HYPERLINK("https://stockanalysis.com/stocks/hubs/statistics/","Open ↗") -> Open ↗ | E15: 2026-07-17 | F15: refresh_market_data.py scales by live price ratio
A16: VALUATION & INDUSTRY BENCHMARKS
A17: Comp fundamentals · Salesforce (FY ended 1/26) | B17: Competitor Benchmarking | C17: Salesforce Q4 FY2026 results, Feb 25, 2026 | D17: =HYPERLINK("https://www.salesforce.com/news/press-releases/2026/02/25/fy26-q4-earnings/","Open ↗") -> Open ↗ | E17: 2026-07-20 | F17: Static · update after comp earnings
A18: Comp fundamentals · monday.com (FY2025) | B18: Competitor Benchmarking | C18: monday.com Q4/FY2025 6-K press release, Feb 9, 2026 | D18: =HYPERLINK("https://www.sec.gov/Archives/edgar/data/1845338/000117891326000346/exhibit_99-1.htm","Open ↗") -> Open ↗ | E18: 2026-07-20 | F18: Static · update after comp earnings
A19: SaaS industry medians (growth, margins, EV/NTM revenue buckets) | B19: Competitor Benchmarking | C19: Clouded Judgement 7.10.26 (Altimeter / Jamin Ball); cross-checked vs multiples.vc Jul 2026 | D19: =HYPERLINK("https://cloudedjudgement.substack.com/p/clouded-judgement-71026-own-your","Open ↗") -> Open ↗ | E19: 2026-07-10 | F19: Manual · ask Claude to refresh
A20: FORECAST ASSUMPTIONS
A21: FY2026–FY2030 growth, unit-economics and scenario inputs | B21: Assumptions · Revenue Drivers · Regional Breakdown | C21: Analyst judgment (A. Pardhootman), anchored to disclosed trends | D21: — | E21: 2026-07-20 | F21: Every change is logged on the Version History tab
A23: Conventions: "Static actuals" never change once filed (restated only if the company restates). Market data carries dual stamps; "Data as of" (the market close the values describe) and "Last refreshed" (when the file was last updated). Analyst assumptions are the author's judgment; the Version History tab is the audit trail.
